Advent of FPGA (Verilog or SystemVerilog)/day-1/src/mod100_pipelined.v
module mod100_pipelined (
    input  wire        clk,
    input  wire        rst,
    input  wire [31:0] in_data,
    output reg  [7:0]  rot_by,
    output reg  [9:0]  quotient
);

    // constant = floor(2^32 / 100) = magic number for fast division
    localparam MAGIC = 32'd42949673;
    
    // Since we're pipelining, we need pipeline register to store data
    reg [31:0] in_s0;

    reg [63:0] mult_s1;
    reg [31:0] in_s1;

    reg [31:0] q_s2;
    reg [31:0] in_s2;

    reg [31:0] r_s3;

    // -Stage 1 - Taking the data in
    always @(posedge clk or posedge rst) begin
        if (rst)
            in_s0 <= 0;
        else
            in_s0 <= in_data;
    end

    // Stage 2 - Multiplying the magic number and storing into S1
    always @(posedge clk or posedge rst) begin
        if (rst) begin
            mult_s1 <= 0;
            in_s1   <= 0;
        end else begin
            mult_s1 <= in_s0 * MAGIC;   // 64-bit product
            in_s1   <= in_s0;
        end
    end

    // Stage 3 - Bit shifting down to get the approximate quotient
    always @(posedge clk or posedge rst) begin
        if (rst) begin
            q_s2 <= 0;
            in_s2 <= 0;
        end else begin
            q_s2 <= mult_s1 >> 32;      // approximate quotient
            in_s2 <= in_s1;
        end
    end

    // Getting the final output by pushing it into the correct range.
    always @(posedge clk or posedge rst) begin
        if (rst) begin
            r_s3   <= 0;
            rot_by <= 0;
            quotient <= 0;
        end else begin
            // compute remainder
            rot_by <= (in_s2 - (q_s2 * 32'd100)) & 32'h000000FF;
            quotient <= q_s2[9:0];
        end
    end

endmodule

day-1/verilog/src/sol.v
module aoc_day1(
    input  wire [31:0] in_data,
    input  wire        clk,
    input  wire        rst,
    input  wire        dir_r,
    output reg  [31:0] zero_count,
    output reg  [31:0] zero_crossings,
    output reg  [7:0]  curr_pos_op
);

    //Instantiate the mod100 module that I built seperately
    wire [9:0] quotient;
    wire [7:0] rot_by;
    wire [1:0] test;

    mod100_pipelined mod_unit (
        .clk(clk),
        .rst(rst),
        .in_data(in_data),
        .rot_by(rot_by),
        .quotient(quotient)
    );

    //To make this work, we need the current and next for arithmatic.
    //The next will then be assigned out to the output
    reg [7:0] curr_pos = 8'd50;
    reg [7:0] next_pos;
    reg [8:0] next_pos_raw;
    reg [3:0] dir_r_reg;

    reg [31:0] test_reg;
    reg zero_crossing_detected = 1'b0;
    reg [11:0] count_cycles= 1'b0;

    //Latency of 4 clock cycles exists because of the mod100 pipeline.
    //Dir_r needs to be delayed the same amount to line up correctly.
    always @(posedge clk or posedge rst) begin
        test_reg <= in_data;
        if (rst) begin
            dir_r_reg <= 5'b0;
        end
        else begin
            dir_r_reg <= {dir_r_reg[3:0], dir_r};
            count_cycles <= count_cycles + 1;
        end
    end

    //Next state logic using comb because it's easier.
    always @(*) begin
        if (dir_r_reg[3]) begin
            next_pos = curr_pos + rot_by;
            next_pos_raw = next_pos;
            if((next_pos_raw > 100 ) & (curr_pos != 0)) begin
                zero_crossing_detected = 1;
                //zero_crossings = zero_crossings + 1; 
            end
            else begin
                zero_crossing_detected = 0;
            end
        end
        else begin
            next_pos_raw = curr_pos - rot_by;
            next_pos = curr_pos + (8'd100 - rot_by);
            if((next_pos_raw[8]) & (curr_pos != 0)) begin
                zero_crossing_detected = 1;
                //zero_crossings = zero_crossings + 1; 
            end
            else begin
                zero_crossing_detected = 0;
            end
        end
        if (next_pos >= 8'd100)
            next_pos = next_pos - 8'd100;
    end

    //Tadaaa, the final sequential block to update state.
    always @(posedge clk or posedge rst) begin
        if (rst) begin
            curr_pos    <= 8'd50;
            zero_count  <= 0;
            curr_pos_op <= 8'd50;
            zero_crossing_detected <= 1'b0;
            zero_crossings <= 0;
        end
        else begin
            curr_pos    <= next_pos;
            curr_pos_op <= next_pos;
            zero_count  <= (next_pos == 0) ? zero_count + 1 : zero_count;
            zero_crossings <= zero_crossings + quotient + zero_crossing_detected;
        end
    end

endmodule

day-1/verilog/src/testbenches/sol_test/sol_tb_test.v
`timescale 1ns / 1ps

module aoc_day1_tb();

    // Instantiate DUT inputs
    reg  [31:0] data_in = 32'b0;
    reg         clk     = 1'b0;
    reg         rst     = 1'b0;
    reg         dir_r   = 1'b0;

    wire [7:0]  curr_pos_op;
    wire [31:0] zero_count;
    wire [31:0] zero_crossings;

    // Instantiate DUT
    aoc_day1 sol_module (
        .in_data(data_in),
        .clk(clk),
        .rst(rst),
        .dir_r(dir_r),
        .zero_count(zero_count),
        .curr_pos_op(curr_pos_op),
        .zero_crossings(zero_crossings)
    );

    //Clock generation
    initial clk = 0;
    always #5 clk = ~clk; // 10 time units clock period

    initial begin
        $dumpfile("aoc_day1_part1_test.vcd");
        $dumpvars(0, aoc_day1_tb);
        
        @(posedge clk)
        rst = 1;
        data_in = 32'b0;
        dir_r = 1'b0;

        @(posedge clk)
        rst = 0;

        //Now the actual data
        @(posedge clk); dir_r = 0; data_in = 68;
        @(posedge clk); dir_r = 0; data_in = 30;
        @(posedge clk); dir_r = 1; data_in = 48;
        @(posedge clk); dir_r = 0; data_in = 5;
        @(posedge clk); dir_r = 1; data_in = 60;
        @(posedge clk); dir_r = 0; data_in = 55;
        @(posedge clk); dir_r = 0; data_in = 1;
        @(posedge clk); dir_r = 0; data_in = 99;
        @(posedge clk); dir_r = 1; data_in = 14;
        @(posedge clk); dir_r = 0; data_in = 82;
        @(posedge clk); dir_r = 0; data_in = 0;

        //Ending the simulation
        repeat(6) @(posedge clk);
        $display("Simulation Ended. Final Zero Count = %0d", zero_count);
        $display("Final Position = %0d", curr_pos_op);
        $display("Final Zero Crossings = %0d", zero_crossings);

        $finish;
    end

endmodule

day-1/verilog/src/testbenches/sol_test/aoc_day1_part1_test.vcd
$date
	Sun Dec 14 15:56:48 2025
$end
$version
	Icarus Verilog
$end
$timescale
	1ps
$end
$scope module aoc_day1_tb $end
$var wire 32 ! zero_crossings [31:0] $end
$var wire 32 " zero_count [31:0] $end
$var wire 8 # curr_pos_op [7:0] $end
$var reg 1 $ clk $end
$var reg 32 % data_in [31:0] $end
$var reg 1 & dir_r $end
$var reg 1 ' rst $end
$scope module sol_module $end
$var wire 1 $ clk $end
$var wire 1 & dir_r $end
$var wire 32 ( in_data [31:0] $end
$var wire 1 ' rst $end
$var wire 8 ) rot_by [7:0] $end
$var wire 10 * quotient [9:0] $end
$var reg 12 + count_cycles [11:0] $end
$var reg 8 , curr_pos [7:0] $end
$var reg 8 - curr_pos_op [7:0] $end
$var reg 4 . dir_r_reg [3:0] $end
$var reg 8 / next_pos [7:0] $end
$var reg 9 0 next_pos_raw [8:0] $end
$var reg 32 1 test_reg [31:0] $end
$var reg 32 2 zero_count [31:0] $end
$var reg 1 3 zero_crossing_detected $end
$var reg 32 4 zero_crossings [31:0] $end
$scope module mod_unit $end
$var wire 1 $ clk $end
$var wire 32 5 in_data [31:0] $end
$var wire 1 ' rst $end
$var parameter 32 6 MAGIC $end
$var reg 32 7 in_s0 [31:0] $end
$var reg 32 8 in_s1 [31:0] $end
$var reg 32 9 in_s2 [31:0] $end
$var reg 64 : mult_s1 [63:0] $end
$var reg 32 ; q_s2 [31:0] $end
$var reg 10 < quotient [9:0] $end
$var reg 32 = r_s3 [31:0] $end
$var reg 8 > rot_by [7:0] $end
$upscope $end
$upscope $end
$upscope $end
$enddefinitions $end
$comment Show the parameter values. $end
$dumpall
b10100011110101110000101001 6
$end
#0
$dumpvars
bx >
bx =
bx <
bx ;
bx :
bx 9
bx 8
bx 7
b0 5
bx 4
03
bx 2
bx 1
bx 0
bx /
bx .
bx -
b110010 ,
b0 +
bx *
bx )
b0 (
0'
0&
b0 %
0$
bx #
bx "
bx !
$end
#5000
b110010 /
b110010 0
b0 7
b0 8
b0 :
b0 9
b0 ;
b0 *
b0 <
b0 )
b0 >
b0 =
b0 .
b0 1
b0 !
b0 4
b110010 #
b110010 -
b0 "
b0 2
1'
1$
#10000
0$
#15000
b1 +
0'
1$
#20000
0$
#25000
b1000100 7
b10 +
b1000100 1
b1000100 %
b1000100 (
b1000100 5
1$
#30000
0$
#35000
b11 +
b11110 1
b1000100 8
b10101110000101000111101011100100 :
b11110 7
b11110 %
b11110 (
b11110 5
1$
#40000
0$
#45000
b110010 /
b110000 7
b11110 8
b1001100110011001100110011001110 :
b1000100 9
b100 +
b1 .
b110000 1
b110000 %
b110000 (
b110000 5
1&
1$
#50000
0$
#55000
13
b1010010 /
b111101110 0
b101 +
b10 .
b101 1
b1000100 )
b1000100 >
b11110 9
b110000 8
b1111010111000010100011110110000 :
b101 7
b101 %
b101 (
b101 5
0&
1$
#60000
0$
#65000
03
b110100 /
b110100 0
b111100 7
b101 8
b1100110011001100110011001101 :
b110000 9
b11110 )
b11110 >
b110 +
b101 .
b111100 1
b1 !
b1 4
b1010010 #
b1010010 -
b1010010 ,
b111100 %
b111100 (
b111100 5
1&
1$
#70000
0$
#75000
b1100100 0
b0 /
b110100 #
b110100 -
b110100 ,
b111 +
b1010 .
b110111 1
b110000 )
b110000 >
b101 9
b111100 8
b10011001100110011001100110011100 :
b110111 7
b110111 %
b110111 (
b110111 5
0&
1$
#80000
0$
#85000
b1011111 /
b111111011 0
b1 7
b110111 8
b10001100110011001100110011001111 :
b111100 9
b101 )
b101 >
b1000 +
b100 .
b1 1
b1 "
b1 2
b0 #
b0 -
b0 ,
b1 %
b1 (
b1 5
1$
#90000
0$
#95000
13
b10011011 0
b110111 /
b1011111 #
b1011111 -
b1011111 ,
b1001 +
b1000 .
b1100011 1
b111100 )
b111100 >
b110111 9
b1 8
b10100011110101110000101001 :
b1100011 7
b1100011 %
b1100011 (
b1100011 5
1$
#100000
0$
#105000
03
b0 /
b0 0
b1110 7
b1100011 8
b11111101011100001010001111011011 :
b1 9
b110111 )
b110111 >
b1010 +
b1 .
b1110 1
b10 !
b10 4
b110111 #
b110111 -
b110111 ,
b1110 %
b1110 (
b1110 5
1&
1$
#110000
0$
#115000
b1100011 /
b111111111 0
b10 "
b10 2
b0 #
b0 -
b0 ,
b1011 +
b10 .
b1010010 1
b1 )
b1 >
b1100011 9
b1110 8
b100011110101110000101000111110 :
b1010010 7
b1010010 %
b1010010 (
b1010010 5
0&
1$
#120000
0$
#125000
b0 /
b0 0
b0 7
b1010010 8
b11010001111010111000010100100010 :
b1110 9
b1100011 )
b1100011 >
b1100 +
b100 .
b0 1
b1100011 #
b1100011 -
b1100011 ,
b0 %
b0 (
b0 5
1$
#130000
0$
#135000
b1110 0
b1110 /
b11 "
b11 2
b0 #
b0 -
b0 ,
b1101 +
b1000 .
b1110 )
b1110 >
b1010010 9
b0 8
b0 :
1$
#140000
0$
#145000
13
b100000 /
b110111100 0
b0 9
b1010010 )
b1010010 >
b1110 +
b0 .
b1110 #
b1110 -
b1110 ,
1$
#150000
0$
#155000
03
b100000 /
b100000 0
b11 !
b11 4
b100000 #
b100000 -
b100000 ,
b1111 +
b0 )
b0 >
1$
#160000
0$
#165000
b10000 +
1$
#170000
0$
#175000
b10001 +
1$
#180000
0$
#185000
b10010 +
1$
