day-1/hardcaml/verilog/top.v
module mod100 (
    rst,
    clk,
    data_in,
    rot_by
);

    input rst;
    input clk;
    input [31:0] data_in;
    output [7:0] rot_by;

    wire [31:0] _27;
    wire [31:0] _23;
    wire [95:0] _18;
    wire [63:0] _16;
    wire [95:0] _17;
    reg [95:0] _19;
    wire [31:0] _20;
    reg [31:0] _22;
    wire [63:0] _24;
    wire _2;
    wire _4;
    wire [31:0] _6;
    reg [31:0] _10;
    reg [31:0] _12;
    reg [31:0] _14;
    wire [63:0] _15;
    wire [63:0] _25;
    wire [31:0] _26;
    reg [31:0] _28;
    wire [7:0] _29;
    assign _27 = 32'b00000000000000000000000000000000;
    assign _23 = 32'b00000000000000000000000001100100;
    assign _18 = 96'b000000000000000000000000000000000000000000000000000000000000000000000000000000000000000000000000;
    assign _16 = 64'b0000000000000000000000000000000000000010100011110101110000101001;
    assign _17 = _10 * _16;
    always @(posedge _4) begin
        if (_2)
            _19 <= _18;
        else
            _19 <= _17;
    end
    assign _20 = _19[63:32];
    always @(posedge _4) begin
        if (_2)
            _22 <= _27;
        else
            _22 <= _20;
    end
    assign _24 = _22 * _23;
    assign _2 = rst;
    assign _4 = clk;
    assign _6 = data_in;
    always @(posedge _4) begin
        if (_2)
            _10 <= _27;
        else
            _10 <= _6;
    end
    always @(posedge _4) begin
        if (_2)
            _12 <= _27;
        else
            _12 <= _10;
    end
    always @(posedge _4) begin
        if (_2)
            _14 <= _27;
        else
            _14 <= _12;
    end
    assign _15 = { _27,
                   _14 };
    assign _25 = _15 - _24;
    assign _26 = _25[31:0];
    always @(posedge _4) begin
        if (_2)
            _28 <= _27;
        else
            _28 <= _26;
    end
    assign _29 = _28[7:0];
    assign rot_by = _29;

endmodule
module top (
    in_data,
    rst,
    clk,
    dir_r,
    zero_count,
    curr_pos_op,
    dir_r_reg,
    zero_crossings
);

    input [31:0] in_data;
    input rst;
    input clk;
    input dir_r;
    output [31:0] zero_count;
    output [7:0] curr_pos_op;
    output [3:0] dir_r_reg;
    output [31:0] zero_crossings;

    wire [31:0] _18;
    wire [31:0] _46;
    wire [8:0] _40;
    wire gnd;
    wire [8:0] _39;
    wire [8:0] _41;
    wire [8:0] _37;
    wire _42;
    wire _43;
    wire [7:0] _33;
    wire _34;
    wire _35;
    wire [7:0] _31;
    wire _32;
    wire _36;
    wire _44;
    wire [31:0] _47;
    wire [63:0] _22;
    wire [63:0] _21;
    wire [127:0] _23;
    wire [31:0] _24;
    wire [31:0] _25;
    wire [31:0] _48;
    wire [31:0] _1;
    reg [31:0] _19;
    wire [31:0] _68;
    wire [7:0] _29;
    wire [7:0] _60;
    wire [7:0] _61;
    wire [7:0] _55;
    wire [31:0] _6;
    wire [7:0] _49;
    wire [7:0] _7;
    wire [7:0] _52;
    wire [7:0] _54;
    wire [3:0] _26;
    wire _9;
    wire _11;
    wire _13;
    wire [2:0] _50;
    wire [3:0] _51;
    wire [3:0] _14;
    reg [3:0] _27;
    wire _28;
    wire [7:0] _56;
    wire _58;
    wire _59;
    wire [7:0] _62;
    wire [7:0] _15;
    reg [7:0] _30 = 8'b00110010;
    wire _64;
    wire [31:0] _69;
    wire [31:0] _16;
    reg [31:0] _66;
    assign _18 = 32'b00000000000000000000000000000000;
    assign _46 = 32'b00000000000000000000000000000001;
    assign _40 = { gnd,
                   _7 };
    assign gnd = 1'b0;
    assign _39 = { gnd,
                   _30 };
    assign _41 = _39 + _40;
    assign _37 = 9'b001100100;
    assign _42 = _37 < _41;
    assign _43 = _42 & _35;
    assign _33 = 8'b00000000;
    assign _34 = _30 == _33;
    assign _35 = ~ _34;
    assign _31 = _30 - _7;
    assign _32 = _31[7:7];
    assign _36 = _32 & _35;
    assign _44 = _28 ? _43 : _36;
    assign _47 = _44 ? _46 : _18;
    assign _22 = 64'b0000000000000000000000000000000000000010100011110101110000101000;
    assign _21 = { _18,
                   _6 };
    assign _23 = _21 * _22;
    assign _24 = _23[63:32];
    assign _25 = _19 + _24;
    assign _48 = _25 + _47;
    assign _1 = _48;
    always @(posedge _11) begin
        if (_9)
            _19 <= _18;
        else
            _19 <= _1;
    end
    assign _68 = _66 + _46;
    assign _29 = 8'b00110010;
    assign _60 = 8'b01100100;
    assign _61 = _56 - _60;
    assign _55 = _30 + _7;
    assign _6 = in_data;
    mod100
        mod100
        ( .clk(_11),
          .rst(_9),
          .data_in(_6),
          .rot_by(_49[7:0]) );
    assign _7 = _49;
    assign _52 = _30 - _7;
    assign _54 = _52 + _60;
    assign _26 = 4'b0000;
    assign _9 = rst;
    assign _11 = clk;
    assign _13 = dir_r;
    assign _50 = _27[2:0];
    assign _51 = { _50,
                   _13 };
    assign _14 = _51;
    always @(posedge _11) begin
        if (_9)
            _27 <= _26;
        else
            _27 <= _14;
    end
    assign _28 = _27[3:3];
    assign _56 = _28 ? _55 : _54;
    assign _58 = _56 < _60;
    assign _59 = ~ _58;
    assign _62 = _59 ? _61 : _56;
    assign _15 = _62;
    always @(posedge _11 or posedge _9) begin
        if (_9)
            _30 <= _29;
        else
            _30 <= _15;
    end
    assign _64 = _30 == _33;
    assign _69 = _64 ? _68 : _66;
    assign _16 = _69;
    always @(posedge _11) begin
        if (_9)
            _66 <= _18;
        else
            _66 <= _16;
    end
    assign zero_count = _66;
    assign curr_pos_op = _30;
    assign dir_r_reg = _27;
    assign zero_crossings = _19;

endmodule
module aoc_day1_part1 (
    in_data,
    dir_r,
    rst,
    clk,
    zero_count,
    curr_pos_op,
    dir_r_reg,
    zero_crossings
);

    input [31:0] in_data;
    input dir_r;
    input rst;
    input clk;
    output [31:0] zero_count;
    output [7:0] curr_pos_op;
    output [3:0] dir_r_reg;
    output [31:0] zero_crossings;

    wire [31:0] _14;
    wire [3:0] _15;
    wire [7:0] _16;
    wire [31:0] _5;
    wire _7;
    wire _9;
    wire _11;
    wire [75:0] _13;
    wire [31:0] _17;
    assign _14 = _13[75:44];
    assign _15 = _13[43:40];
    assign _16 = _13[39:32];
    assign _5 = in_data;
    assign _7 = dir_r;
    assign _9 = rst;
    assign _11 = clk;
    top
        top
        ( .clk(_11),
          .rst(_9),
          .dir_r(_7),
          .in_data(_5),
          .zero_count(_13[31:0]),
          .curr_pos_op(_13[39:32]),
          .dir_r_reg(_13[43:40]),
          .zero_crossings(_13[75:44]) );
    assign _17 = _13[31:0];
    assign zero_count = _17;
    assign curr_pos_op = _16;
    assign dir_r_reg = _15;
    assign zero_crossings = _14;

endmodule

day-1/verilog/src/testbenches/sol_test/sol_tb_test.v
`timescale 1ns / 1ps

module aoc_day1_tb();

    // Instantiate DUT inputs
    reg  [31:0] data_in = 32'b0;
    reg         clk     = 1'b0;
    reg         rst     = 1'b0;
    reg         dir_r   = 1'b0;

    wire [7:0]  curr_pos_op;
    wire [31:0] zero_count;
    wire [31:0] zero_crossings;

    // Instantiate DUT
    aoc_day1_part1 sol_module (
        .in_data(data_in),
        .clk(clk),
        .rst(rst),
        .dir_r(dir_r),
        .zero_count(zero_count),
        .curr_pos_op(curr_pos_op),
        .zero_crossings(zero_crossings)
    );

    //Clock generation
    initial clk = 0;
    always #5 clk = ~clk; // 10 time units clock period

    initial begin
        $dumpfile("aoc_day1_part1_test.vcd");
        $dumpvars(0, aoc_day1_tb);
        
        @(posedge clk)
        rst = 1;
        data_in = 32'b0;
        dir_r = 1'b0;

        @(posedge clk)
        rst = 0;

        //Now the actual data
        @(posedge clk); dir_r = 0; data_in = 68;
        @(posedge clk); dir_r = 0; data_in = 30;
        @(posedge clk); dir_r = 1; data_in = 48;
        @(posedge clk); dir_r = 0; data_in = 5;
        @(posedge clk); dir_r = 1; data_in = 60;
        @(posedge clk); dir_r = 0; data_in = 55;
        @(posedge clk); dir_r = 0; data_in = 1;
        @(posedge clk); dir_r = 0; data_in = 99;
        @(posedge clk); dir_r = 1; data_in = 14;
        @(posedge clk); dir_r = 0; data_in = 82;
        @(posedge clk); dir_r = 0; data_in = 0;

        //Ending the simulation
        repeat(6) @(posedge clk);
        $display("Simulation Ended. Final Zero Count = %0d", zero_count);
        $display("Final Position = %0d", curr_pos_op);
        $display("Final Zero Crossings = %0d", zero_crossings);

        $finish;
    end

endmodule

day-1/verilog/src/testbenches/sol_test/aoc_day1_part1_test.vcd
$date
	Mon Dec 15 22:25:48 2025
$end
$version
	Icarus Verilog
$end
$timescale
	1ps
$end
$scope module aoc_day1_tb $end
$var wire 32 ! zero_crossings [31:0] $end
$var wire 32 " zero_count [31:0] $end
$var wire 8 # curr_pos_op [7:0] $end
$var reg 1 $ clk $end
$var reg 32 % data_in [31:0] $end
$var reg 1 & dir_r $end
$var reg 1 ' rst $end
$scope module sol_module $end
$var wire 1 ( _11 $end
$var wire 32 ) _5 [31:0] $end
$var wire 1 * _7 $end
$var wire 1 + _9 $end
$var wire 1 $ clk $end
$var wire 8 , curr_pos_op [7:0] $end
$var wire 1 & dir_r $end
$var wire 4 - dir_r_reg [3:0] $end
$var wire 32 . in_data [31:0] $end
$var wire 1 ' rst $end
$var wire 32 / zero_count [31:0] $end
$var wire 32 0 zero_crossings [31:0] $end
$var wire 32 1 _17 [31:0] $end
$var wire 8 2 _16 [7:0] $end
$var wire 4 3 _15 [3:0] $end
$var wire 32 4 _14 [31:0] $end
$var wire 76 5 _13 [75:0] $end
$scope module top $end
$var wire 32 6 _1 [31:0] $end
$var wire 1 7 _11 $end
$var wire 1 8 _13 $end
$var wire 4 9 _14 [3:0] $end
$var wire 8 : _15 [7:0] $end
$var wire 32 ; _16 [31:0] $end
$var wire 32 < _18 [31:0] $end
$var wire 64 = _22 [63:0] $end
$var wire 4 > _26 [3:0] $end
$var wire 8 ? _29 [7:0] $end
$var wire 8 @ _33 [7:0] $end
$var wire 1 A _35 $end
$var wire 1 B _36 $end
$var wire 9 C _37 [8:0] $end
$var wire 1 D _43 $end
$var wire 32 E _46 [31:0] $end
$var wire 1 F _59 $end
$var wire 32 G _6 [31:0] $end
$var wire 8 H _60 [7:0] $end
$var wire 8 I _7 [7:0] $end
$var wire 1 J _9 $end
$var wire 1 ( clk $end
$var wire 8 K curr_pos_op [7:0] $end
$var wire 1 * dir_r $end
$var wire 4 L dir_r_reg [3:0] $end
$var wire 1 M gnd $end
$var wire 32 N in_data [31:0] $end
$var wire 1 + rst $end
$var wire 32 O zero_count [31:0] $end
$var wire 32 P zero_crossings [31:0] $end
$var wire 32 Q _69 [31:0] $end
$var wire 32 R _68 [31:0] $end
$var wire 1 S _64 $end
$var wire 8 T _62 [7:0] $end
$var wire 8 U _61 [7:0] $end
$var wire 1 V _58 $end
$var wire 8 W _56 [7:0] $end
$var wire 8 X _55 [7:0] $end
$var wire 8 Y _54 [7:0] $end
$var wire 8 Z _52 [7:0] $end
$var wire 4 [ _51 [3:0] $end
$var wire 3 \ _50 [2:0] $end
$var wire 8 ] _49 [7:0] $end
$var wire 32 ^ _48 [31:0] $end
$var wire 32 _ _47 [31:0] $end
$var wire 1 ` _44 $end
$var wire 1 a _42 $end
$var wire 9 b _41 [8:0] $end
$var wire 9 c _40 [8:0] $end
$var wire 9 d _39 [8:0] $end
$var wire 1 e _34 $end
$var wire 1 f _32 $end
$var wire 8 g _31 [7:0] $end
$var wire 1 h _28 $end
$var wire 32 i _25 [31:0] $end
$var wire 32 j _24 [31:0] $end
$var wire 128 k _23 [127:0] $end
$var wire 64 l _21 [63:0] $end
$var reg 32 m _19 [31:0] $end
$var reg 4 n _27 [3:0] $end
$var reg 8 o _30 [7:0] $end
$var reg 32 p _66 [31:0] $end
$scope module mod100 $end
$var wire 64 q _16 [63:0] $end
$var wire 96 r _18 [95:0] $end
$var wire 1 s _2 $end
$var wire 32 t _23 [31:0] $end
$var wire 32 u _27 [31:0] $end
$var wire 1 v _4 $end
$var wire 32 w _6 [31:0] $end
$var wire 1 7 clk $end
$var wire 32 x data_in [31:0] $end
$var wire 8 y rot_by [7:0] $end
$var wire 1 J rst $end
$var wire 8 z _29 [7:0] $end
$var wire 32 { _26 [31:0] $end
$var wire 64 | _25 [63:0] $end
$var wire 64 } _24 [63:0] $end
$var wire 32 ~ _20 [31:0] $end
$var wire 96 !" _17 [95:0] $end
$var wire 64 "" _15 [63:0] $end
$var reg 32 #" _10 [31:0] $end
$var reg 32 $" _12 [31:0] $end
$var reg 32 %" _14 [31:0] $end
$var reg 96 &" _19 [95:0] $end
$var reg 32 '" _22 [31:0] $end
$var reg 32 (" _28 [31:0] $end
$upscope $end
$upscope $end
$upscope $end
$upscope $end
$enddefinitions $end
$comment Show the parameter values. $end
$dumpall
$end
#0
$dumpvars
bx ("
bx '"
bx &"
bx %"
bx $"
bx #"
b0xxxxxxxxxxxxxxxxxxxxxxxxxxxxxxxx ""
bx !"
bx ~
bx }
bx |
bx {
bx z
bx y
b0 x
b0 w
0v
b0 u
b1100100 t
0s
b0 r
b10100011110101110000101001 q
bx p
b110010 o
bx n
bx m
b0 l
b0 k
b0 j
bx i
xh
bx g
xf
0e
b110010 d
b0xxxxxxxx c
bx b
xa
x`
b0x _
bx ^
bx ]
bx \
bx0 [
bx Z
bx Y
bx X
bx W
xV
bx U
bx T
0S
bx R
bx Q
bx P
bx O
b0 N
0M
bx L
b110010 K
0J
bx I
b1100100 H
b0 G
xF
b1 E
xD
b1100100 C
xB
1A
b0 @
b110010 ?
b0 >
b10100011110101110000101000 =
b0 <
bx ;
bx :
bx0 9
08
07
bx 6
bx00110010xxxxxxxxxxxxxxxxxxxxxxxxxxxxxxxx 5
bx 4
bx 3
b110010 2
bx 1
bx 0
bx /
b0 .
bx -
b110010 ,
0+
0*
b0 )
0(
0'
0&
b0 %
0$
b110010 #
bx "
bx !
$end
#5000
b0 6
b0 ^
b0 _
0`
0B
1F
b110010 :
b110010 T
0D
0f
0V
b110010 U
b10010110 W
b0 ~
b0 {
0a
b110010 b
b0 c
b110010 g
b110010 X
b10010110 Y
b110010 Z
b0 I
b0 ]
b0 y
b0 z
b0 !
b0 0
b0 4
b0 9
b0 [
b0 \
0h
b0 -
b0 3
b0 ;
b0 Q
b0 "
b0 /
b0 1
b0 &"
b0 |
b0 }
b0 '"
b0 !"
b0 #"
b0 $"
b0 ""
b0 %"
b0 ("
b0 i
b0 P
b0 m
b0 L
b0 n
b1 R
b11001000000000000000000000000000000000 5
b0 O
b0 p
1s
1J
1+
1'
1v
17
1(
1$
#10000
0v
07
0(
0$
#15000
0s
0J
0+
0'
1v
17
1(
1$
#20000
0v
07
0(
0$
#25000
b10101110000101000111101011100100 !"
b1000100 #"
b10101110000101000111101010100000 k
b1000100 l
b1000100 w
b1000100 G
b1000100 x
b1000100 )
b1000100 N
b1000100 %
b1000100 .
1v
17
1(
1$
#30000
0v
07
0(
0$
#35000
b1000100 $"
b1001100110011001100110011001110 !"
b11110 #"
b10101110000101000111101011100100 &"
b1001100110011001100110010110000 k
b11110 l
b11110 w
b11110 G
b11110 x
b11110 )
b11110 N
b11110 %
b11110 .
1v
17
1(
1$
#40000
0v
07
0(
0$
#45000
b1000100 {
b1 \
b1 -
b1 3
b1001100110011001100110011001110 &"
b1111010111000010100011110110000 !"
b110000 #"
b11110 $"
b1000100 |
b1000100 ""
b1000100 %"
b10011001000000000000000000000000000000000 5
b1 L
b1 n
b1111010111000010100011110000000 k
b110000 l
b110000 w
b110000 G
b110000 x
b110000 )
b110000 N
b110000 %
b110000 .
b11 9
b11 [
18
1*
1&
1v
17
1(
1$
#50000
0v
07
0(
0$
#55000
b1 6
b1 ^
b1 _
1`
1B
0F
b1010010 :
b1010010 T
1D
1f
1V
b11101110 U
b1010010 W
1a
b1110110 b
b1000100 c
b11101110 g
b1110110 X
b1010010 Y
b11101110 Z
b1000100 I
b1000100 ]
b1000100 y
b1000100 z
b11110 {
b10 \
b10 -
b10 3
b1000100 ("
b11110 |
b11110 ""
b11110 %"
b110000 $"
b1100110011001100110011001101 !"
b101 #"
b1111010111000010100011110110000 &"
b100011001000000000000000000000000000000000 5
b10 L
b10 n
b1100110011001100110011001000 k
b101 l
b101 w
b101 G
b101 x
b101 )
b101 N
b101 %
b101 .
b100 9
b100 [
08
0*
0&
1v
17
1(
1$
#60000
0v
07
0(
0$
#65000
b0 _
0`
0B
1F
b110100 :
b110100 T
b110000 {
b11110 c
b11110 I
b11110 ]
b11110 y
b11110 z
0f
0V
b110100 U
b10011000 W
b1010010 #
b1010010 ,
b1010010 2
b1 !
b1 0
b1 4
b101 \
b101 -
b101 3
b1100110011001100110011001101 &"
b10011001100110011001100110011100 !"
b111100 #"
b101 $"
b110000 |
b110000 ""
b110000 %"
b11110 ("
b1110000 b
b1010010 d
b110100 g
b1110000 X
b10011000 Y
b110100 Z
b1010010 K
b1010010 o
b1 6
b1 ^
b1 i
b1 P
b1 m
b101010101001000000000000000000000000000000000 5
b101 L
b101 n
b10011001100110011001100101100000 k
b111100 l
b111100 w
b111100 G
b111100 x
b111100 )
b111100 N
b111100 %
b111100 .
b1011 9
b1011 [
18
1*
1&
1v
17
1(
1$
#70000
0v
07
0(
0$
#75000
1F
b0 :
b0 T
b110000 c
b110000 I
b110000 ]
b110000 y
b110000 z
b101 {
0D
0V
b0 U
b1100100 W
b110100 #
b110100 ,
b110100 2
b10 \
1h
b1010 -
b1010 3
b110000 ("
b101 |
b101 ""
b101 %"
b111100 $"
b10001100110011001100110011001111 !"
b110111 #"
b10011001100110011001100110011100 &"
0a
b1100100 b
b110100 d
b100 g
b1100100 X
b1101000 Y
b100 Z
b110100 K
b110100 o
b110100011010000000000000000000000000000000000 5
b1010 L
b1010 n
b10001100110011001100110010011000 k
b110111 l
b110111 w
b110111 G
b110111 x
b110111 )
b110111 N
b110111 %
b110111 .
b100 9
b100 [
08
0*
0&
1v
17
1(
1$
#80000
0v
07
0(
0$
#85000
0F
b1011111 :
b1011111 T
b111100 {
b101 c
b101 I
b101 ]
b101 y
b101 z
0A
1f
1V
b11111011 U
b1011111 W
b1 ;
b1 Q
b0 #
b0 ,
b0 2
b1000 9
b1000 [
b100 \
0h
b100 -
b100 3
b10001100110011001100110011001111 &"
b10100011110101110000101001 !"
b1 #"
b110111 $"
b111100 |
b111100 ""
b111100 %"
b101 ("
b101 b
b0 d
1e
b11111011 g
b101 X
b1011111 Y
b11111011 Z
1S
b0 K
b0 o
b101000000000000000000000000000000000000000000 5
b100 L
b100 n
b10100011110101110000101000 k
b1 l
b1 w
b1 G
b1 x
b1 )
b1 N
b1 %
b1 .
1v
17
1(
1$
#90000
0v
07
0(
0$
#95000
b10 6
b10 ^
b1 _
1`
1D
1F
b110111 :
b110111 T
1a
b111100 c
b111100 I
b111100 ]
b111100 y
b111100 z
b110111 {
1A
0f
0V
b110111 U
b10011011 W
b1011111 #
b1011111 ,
b1011111 2
b1 "
b1 /
b1 1
b0 9
b0 [
b0 \
1h
b1000 -
b1000 3
b111100 ("
b110111 |
b110111 ""
b110111 %"
b1 $"
b11111101011100001010001111011011 !"
b1100011 #"
b10100011110101110000101001 &"
b10011011 b
b1011111 d
0e
b100011 g
b10011011 X
b10000111 Y
b100011 Z
0S
b1011111 K
b1011111 o
b10 R
b1 O
b1 p
b110000101111100000000000000000000000000000001 5
b1000 L
b1000 n
b11111101011100001010001101111000 k
b1100011 l
b1100011 w
b1100011 G
b1100011 x
b1100011 )
b1100011 N
b1100011 %
b1100011 .
1v
17
1(
1$
#100000
0v
07
0(
0$
#105000
b0 _
0B
1F
b0 :
b0 T
0`
b1 {
b110111 c
b110111 I
b110111 ]
b110111 y
b110111 z
0f
0V
b0 U
b1100100 W
b110111 #
b110111 ,
b110111 2
b10 !
b10 0
b10 4
b1 \
0h
b1 -
b1 3
b11111101011100001010001111011011 &"
b100011110101110000101000111110 !"
b1110 #"
b1100011 $"
b1 |
b1 ""
b1 %"
b110111 ("
b1101110 b
b110111 d
b0 g
b1101110 X
b1100100 Y
b0 Z
b110111 K
b110111 o
b10 6
b10 ^
b10 i
b10 P
b10 m
b1000010011011100000000000000000000000000000001 5
b1 L
b1 n
b100011110101110000101000110000 k
b1110 l
b1110 w
b1110 G
b1110 x
b1110 )
b1110 N
b1110 %
b1110 .
b11 9
b11 [
18
1*
1&
1v
17
1(
1$
#110000
0v
07
0(
0$
#115000
0F
b1100011 :
b1100011 T
b1 c
b1 I
b1 ]
b1 y
b1 z
b1100011 {
0D
0A
1f
1V
b11111111 U
b1100011 W
b10 ;
b10 Q
b0 #
b0 ,
b0 2
b10 \
b10 -
b10 3
b1 ("
b1100011 |
b1100011 ""
b1100011 %"
b1110 $"
b11010001111010111000010100100010 !"
b1010010 #"
b100011110101110000101000111110 &"
0a
b1 b
b0 d
1e
b11111111 g
b1 X
b1100011 Y
b11111111 Z
1S
b0 K
b0 o
b1000100000000000000000000000000000000000000001 5
b10 L
b10 n
b11010001111010111000010011010000 k
b1010010 l
b1010010 w
b1010010 G
b1010010 x
b1010010 )
b1010010 N
b1010010 %
b1010010 .
b100 9
b100 [
08
0*
0&
1v
17
1(
1$
#120000
0v
07
0(
0$
#125000
1D
1F
b0 :
b0 T
b1110 {
1a
b1100011 c
b1100011 I
b1100011 ]
b1100011 y
b1100011 z
1A
0f
0V
b0 U
b1100100 W
b1100011 #
b1100011 ,
b1100011 2
b1000 9
b1000 [
b100 \
b100 -
b100 3
b10 "
b10 /
b10 1
b11010001111010111000010100100010 &"
b0 !"
b0 #"
b1010010 $"
b1110 |
b1110 ""
b1110 %"
b1100011 ("
b11000110 b
b1100011 d
0e
b0 g
b11000110 X
b1100100 Y
b0 Z
0S
b1100011 K
b1100011 o
b100 L
b100 n
b11 R
b1001000110001100000000000000000000000000000010 5
b10 O
b10 p
b0 k
b0 l
b0 w
b0 G
b0 x
b0 )
b0 N
b0 %
b0 .
1v
17
1(
1$
#130000
0v
07
0(
0$
#135000
0F
b1110 :
b1110 T
b1110 c
b1110 I
b1110 ]
b1110 y
b1110 z
b1010010 {
0D
0A
1f
1V
b10101010 U
b1110 W
b11 ;
b11 Q
b0 #
b0 ,
b0 2
b0 9
b0 [
b0 \
1h
b1000 -
b1000 3
b1110 ("
b1010010 |
b1010010 ""
b1010010 %"
b0 $"
b0 &"
0a
b1110 b
b0 d
1e
b11110010 g
b1110 X
b1010110 Y
b11110010 Z
1S
b0 K
b0 o
b1010000000000000000000000000000000000000000010 5
b1000 L
b1000 n
1v
17
1(
1$
#140000
0v
07
0(
0$
#145000
b11 6
b11 ^
b1 _
1`
1B
0F
b100000 :
b100000 T
b0 {
b1010010 c
b1010010 I
b1010010 ]
b1010010 y
b1010010 z
1A
1f
1V
b10111100 U
b100000 W
b1110 #
b1110 ,
b1110 2
0h
b0 -
b0 3
b11 "
b11 /
b11 1
b0 |
b0 ""
b0 %"
b1010010 ("
b1100000 b
b1110 d
0e
b10111100 g
b1100000 X
b100000 Y
b10111100 Z
0S
b1110 K
b1110 o
b0 L
b0 n
b100 R
b1000000000111000000000000000000000000000000011 5
b11 O
b11 p
1v
17
1(
1$
#150000
0v
07
0(
0$
#155000
b0 _
0`
0B
1F
0f
0V
b100000 :
b100000 T
b0 c
b0 I
b0 ]
b0 y
b0 z
0D
b100000 U
b10000100 W
b100000 #
b100000 ,
b100000 2
b11 !
b11 0
b11 4
b0 ("
0a
b100000 b
b100000 d
b100000 g
b100000 X
b10000100 Y
b100000 Z
b100000 K
b100000 o
b11 6
b11 ^
b11 i
b1100000010000000000000000000000000000000000011 5
b11 P
b11 m
1v
17
1(
1$
#160000
0v
07
0(
0$
#165000
1v
17
1(
1$
#170000
0v
07
0(
0$
#175000
1v
17
1(
1$
#180000
0v
07
0(
0$
#185000
1v
17
1(
1$
