Advent of FPGA (Verilog or SystemVerilog)/day-1/src/mod100_pipelined.v
module mod100_pipelined (
    input  wire        clk,
    input  wire        rst,
    input  wire [31:0] in_data,
    output reg  [7:0]  rot_by,
    output reg  [9:0]  quotient
);

    // constant = floor(2^32 / 100) = magic number for fast division
    localparam MAGIC = 32'd42949673;
    
    // Since we're pipelining, we need pipeline register to store data
    reg [31:0] in_s0;

    reg [63:0] mult_s1;
    reg [31:0] in_s1;

    reg [31:0] q_s2;
    reg [31:0] in_s2;

    reg [31:0] r_s3;

    // -Stage 1 - Taking the data in
    always @(posedge clk or posedge rst) begin
        if (rst)
            in_s0 <= 0;
        else
            in_s0 <= in_data;
    end

    // Stage 2 - Multiplying the magic number and storing into S1
    always @(posedge clk or posedge rst) begin
        if (rst) begin
            mult_s1 <= 0;
            in_s1   <= 0;
        end else begin
            mult_s1 <= in_s0 * MAGIC;   // 64-bit product
            in_s1   <= in_s0;
        end
    end

    // Stage 3 - Bit shifting down to get the approximate quotient
    always @(posedge clk or posedge rst) begin
        if (rst) begin
            q_s2 <= 0;
            in_s2 <= 0;
        end else begin
            q_s2 <= mult_s1 >> 32;      // approximate quotient
            in_s2 <= in_s1;
        end
    end

    // Getting the final output by pushing it into the correct range.
    always @(posedge clk or posedge rst) begin
        if (rst) begin
            r_s3   <= 0;
            rot_by <= 0;
            quotient <= 0;
        end else begin
            // compute remainder
            rot_by <= (in_s2 - (q_s2 * 32'd100)) & 32'h000000FF;
            quotient <= q_s2[9:0];
        end
    end

endmodule

day-1/verilog/src/sol.v
module aoc_day1(
    input  wire [31:0] in_data,
    input  wire        clk,
    input  wire        rst,
    input  wire        dir_r,
    output reg  [31:0] zero_count,
    output reg  [31:0] zero_crossings,
    output reg  [7:0]  curr_pos_op
);

    //Instantiate the mod100 module that I built seperately
    wire [9:0] quotient;
    wire [7:0] rot_by;
    wire [1:0] test;

    mod100_pipelined mod_unit (
        .clk(clk),
        .rst(rst),
        .in_data(in_data),
        .rot_by(rot_by),
        .quotient(quotient)
    );

    //To make this work, we need the current and next for arithmatic.
    //The next will then be assigned out to the output
    reg [7:0] curr_pos = 8'd50;
    reg [7:0] next_pos;
    reg [8:0] next_pos_raw;
    reg [3:0] dir_r_reg;

    reg [31:0] test_reg;
    reg zero_crossing_detected = 1'b0;
    reg [11:0] count_cycles= 1'b0;

    //Latency of 4 clock cycles exists because of the mod100 pipeline.
    //Dir_r needs to be delayed the same amount to line up correctly.
    always @(posedge clk or posedge rst) begin
        test_reg <= in_data;
        if (rst) begin
            dir_r_reg <= 5'b0;
        end
        else begin
            dir_r_reg <= {dir_r_reg[3:0], dir_r};
            count_cycles <= count_cycles + 1;
        end
    end

    //Next state logic using comb because it's easier.
    always @(*) begin
        if (dir_r_reg[3]) begin
            next_pos = curr_pos + rot_by;
            next_pos_raw = next_pos;
            if((next_pos_raw > 100 ) & (curr_pos != 0)) begin
                zero_crossing_detected = 1;
                //zero_crossings = zero_crossings + 1; 
            end
            else begin
                zero_crossing_detected = 0;
            end
        end
        else begin
            next_pos_raw = curr_pos - rot_by;
            next_pos = curr_pos + (8'd100 - rot_by);
            if((next_pos_raw[8]) & (curr_pos != 0)) begin
                zero_crossing_detected = 1;
                //zero_crossings = zero_crossings + 1; 
            end
            else begin
                zero_crossing_detected = 0;
            end
        end
        if (next_pos >= 8'd100)
            next_pos = next_pos - 8'd100;
    end

    //Tadaaa, the final sequential block to update state.
    always @(posedge clk or posedge rst) begin
        if (rst) begin
            curr_pos    <= 8'd50;
            zero_count  <= 0;
            curr_pos_op <= 8'd50;
            zero_crossing_detected <= 1'b0;
            zero_crossings <= 0;
        end
        else begin
            curr_pos    <= next_pos;
            curr_pos_op <= next_pos;
            zero_count  <= (next_pos == 0) ? zero_count + 1 : zero_count;
            zero_crossings <= zero_crossings + quotient + zero_crossing_detected;
        end
    end

endmodule

day-1/verilog/src/testbenches/sol_test/sol_tb_test.v
`timescale 1ns / 1ps

module aoc_day1_tb();

    // Instantiate DUT inputs
    reg  [31:0] data_in = 32'b0;
    reg         clk     = 1'b0;
    reg         rst     = 1'b0;
    reg         dir_r   = 1'b0;

    wire [7:0]  curr_pos_op;
    wire [31:0] zero_count;
    wire [31:0] zero_crossings;

    // Instantiate DUT
    aoc_day1 sol_module (
        .in_data(data_in),
        .clk(clk),
        .rst(rst),
        .dir_r(dir_r),
        .zero_count(zero_count),
        .curr_pos_op(curr_pos_op),
        .zero_crossings(zero_crossings)
    );

    //Clock generation
    initial clk = 0;
    always #5 clk = ~clk; // 10 time units clock period

    initial begin
        $dumpfile("aoc_day1_part1_test.vcd");
        $dumpvars(0, aoc_day1_tb);
        
        @(posedge clk)
        rst = 1;
        data_in = 32'b0;
        dir_r = 1'b0;

        @(posedge clk)
        rst = 0;

        //Now the actual data
        @(posedge clk); dir_r = 0; data_in = 68;
        @(posedge clk); dir_r = 0; data_in = 30;
        @(posedge clk); dir_r = 1; data_in = 48;
        @(posedge clk); dir_r = 0; data_in = 5;
        @(posedge clk); dir_r = 1; data_in = 60;
        @(posedge clk); dir_r = 0; data_in = 55;
        @(posedge clk); dir_r = 0; data_in = 1;
        @(posedge clk); dir_r = 0; data_in = 99;
        @(posedge clk); dir_r = 1; data_in = 14;
        @(posedge clk); dir_r = 0; data_in = 82;
        @(posedge clk); dir_r = 0; data_in = 0;

        //Ending the simulation
        repeat(6) @(posedge clk);
        $display("Simulation Ended. Final Zero Count = %0d", zero_count);
        $display("Final Position = %0d", curr_pos_op);
        $display("Final Zero Crossings = %0d", zero_crossings);

        $finish;
    end

endmodule

day-1/verilog/src/testbenches/sol_test/sol_tb.vcd
$date
	Sun Dec 14 15:56:40 2025
$end
$version
	Icarus Verilog
$end
$timescale
	1ps
$end
$scope module aoc_day1_tb $end
$var wire 32 ! zero_crossings [31:0] $end
$var wire 32 " zero_count [31:0] $end
$var wire 8 # curr_pos_op [7:0] $end
$var reg 1 $ clk $end
$var reg 32 % data_in [31:0] $end
$var reg 1 & dir_r $end
$var reg 1 ' rst $end
$scope module sol_module $end
$var wire 1 $ clk $end
$var wire 1 & dir_r $end
$var wire 32 ( in_data [31:0] $end
$var wire 1 ' rst $end
$var wire 8 ) rot_by [7:0] $end
$var wire 10 * quotient [9:0] $end
$var reg 12 + count_cycles [11:0] $end
$var reg 8 , curr_pos [7:0] $end
$var reg 8 - curr_pos_op [7:0] $end
$var reg 4 . dir_r_reg [3:0] $end
$var reg 8 / next_pos [7:0] $end
$var reg 9 0 next_pos_raw [8:0] $end
$var reg 32 1 test_reg [31:0] $end
$var reg 32 2 zero_count [31:0] $end
$var reg 1 3 zero_crossing_detected $end
$var reg 32 4 zero_crossings [31:0] $end
$scope module mod_unit $end
$var wire 1 $ clk $end
$var wire 32 5 in_data [31:0] $end
$var wire 1 ' rst $end
$var parameter 32 6 MAGIC $end
$var reg 32 7 in_s0 [31:0] $end
$var reg 32 8 in_s1 [31:0] $end
$var reg 32 9 in_s2 [31:0] $end
$var reg 64 : mult_s1 [63:0] $end
$var reg 32 ; q_s2 [31:0] $end
$var reg 10 < quotient [9:0] $end
$var reg 32 = r_s3 [31:0] $end
$var reg 8 > rot_by [7:0] $end
$upscope $end
$upscope $end
$upscope $end
$enddefinitions $end
$comment Show the parameter values. $end
$dumpall
b10100011110101110000101001 6
$end
#0
$dumpvars
bx >
bx =
bx <
bx ;
bx :
bx 9
bx 8
bx 7
b0 5
bx 4
03
bx 2
bx 1
bx 0
bx /
bx .
bx -
b110010 ,
b0 +
bx *
bx )
b0 (
0'
0&
b0 %
0$
bx #
bx "
bx !
$end
#5000
b110010 /
b110010 0
b0 7
b0 8
b0 :
b0 9
b0 ;
b0 *
b0 <
b0 )
b0 >
b0 =
b0 .
b0 1
b0 !
b0 4
b110010 #
b110010 -
b0 "
b0 2
1'
1$
#10000
0$
#15000
b1 +
0'
1$
#20000
0$
#25000
b101 7
b10 +
b101 1
b101 %
b101 (
b101 5
1$
#30000
0$
#35000
b11 +
b100101 1
b101 8
b1100110011001100110011001101 :
b100101 7
b100101 %
b100101 (
b100101 5
1$
#40000
0$
#45000
b100000 7
b100101 8
b1011110101110000101000111101101 :
b101 9
b100 +
b100000 1
b100000 %
b100000 (
b100000 5
1$
#50000
0$
#55000
b101101 /
b101101 0
b101 +
b1 .
b101 1
b101 )
b101 >
b100101 9
b100000 8
b1010001111010111000010100100000 :
b101 7
b101 %
b101 (
b101 5
1&
1$
#60000
0$
#65000
b1000 /
b1000 0
b100100 7
b101 8
b1100110011001100110011001101 :
b100000 9
b100101 )
b100101 >
b110 +
b10 .
b100100 1
b101101 #
b101101 -
b101101 ,
b100100 %
b100100 (
b100100 5
0&
1$
#70000
0$
#75000
13
b1001100 /
b111101000 0
b1000 #
b1000 -
b1000 ,
b111 +
b100 .
b11101 1
b100000 )
b100000 >
b101 9
b100100 8
b1011100001010001111010111000100 :
b11101 7
b11101 %
b11101 (
b11101 5
1$
#80000
0$
#85000
03
b1010001 0
b1010001 /
b1101 7
b11101 8
b1001010001111010111000010100101 :
b100100 9
b101 )
b101 >
b1000 +
b1001 .
b1101 1
b1 !
b1 4
b1001100 #
b1001100 -
b1001100 ,
b1101 %
b1101 (
b1101 5
1&
1$
#90000
0$
#95000
b101101 /
b101101 0
b1010001 #
b1010001 -
b1010001 ,
b1001 +
b11 .
b10001 1
b100100 )
b100100 >
b11101 9
b1101 8
b100001010001111010111000010101 :
b10001 7
b10001 %
b10001 (
b10001 5
1$
#100000
0$
#105000
b10000 /
b10000 0
b10011 7
b10001 8
b101011100001010001111010111001 :
b1101 9
b11101 )
b11101 >
b1010 +
b110 .
b10011 1
b101101 #
b101101 -
b101101 ,
b10011 %
b10011 (
b10011 5
0&
1$
#110000
0$
#115000
b11101 0
b11101 /
b10000 #
b10000 -
b10000 ,
b1011 +
b1100 .
b100010 1
b1101 )
b1101 >
b10001 9
b10011 8
b110000101000111101011100001011 :
b100010 7
b100010 %
b100010 (
b100010 5
1$
#120000
0$
#125000
b101110 0
b101110 /
b10 7
b100010 8
b1010111000010100011110101110010 :
b10011 9
b10001 )
b10001 >
b1100 +
b1001 .
b10 1
b11101 #
b11101 -
b11101 ,
b10 %
b10 (
b10 5
1&
1$
#130000
0$
#135000
b11011 /
b11011 0
b101110 #
b101110 -
b101110 ,
b1101 +
b11 .
b1001 1
b10011 )
b10011 >
b100010 9
b10 8
b101000111101011100001010010 :
b1001 7
b1001 %
b1001 (
b1001 5
1$
#140000
0$
#145000
13
b1011101 /
b111111001 0
b1 7
b1001 8
b10111000010100011110101110001 :
b10 9
b100010 )
b100010 >
b1110 +
b111 .
b1 1
b11011 #
b11011 -
b11011 ,
b1 %
b1 (
b1 5
1$
#150000
0$
#155000
03
b1011111 0
b1011111 /
b10 !
b10 4
b1011101 #
b1011101 -
b1011101 ,
b1111 +
b1111 .
b1011 1
b10 )
b10 >
b1001 9
b1 8
b10100011110101110000101001 :
b1011 7
b1011 %
b1011 (
b1011 5
1$
#160000
0$
#165000
13
b1101000 0
b100 /
b100011 7
b1011 8
b11100001010001111010111000011 :
b1 9
b1001 )
b1001 >
b10000 +
b100011 1
b1011111 #
b1011111 -
b1011111 ,
b100011 %
b100011 (
b100011 5
1$
#170000
0$
#175000
03
b101 0
b101 /
b11 !
b11 4
b100 #
b100 -
b100 ,
b10001 +
b11010 1
b1 )
b1 >
b1011 9
b100011 8
b1011001100110011001100110011011 :
b11010 7
b11010 %
b11010 (
b11010 5
1$
#180000
0$
#185000
b10000 0
b10000 /
b10100 7
b11010 8
b1000010100011110101110000101010 :
b100011 9
b1011 )
b1011 >
b10010 +
b1110 .
b10100 1
b101 #
b101 -
b101 ,
b10100 %
b10100 (
b10100 5
0&
1$
#190000
0$
#195000
b110011 0
b110011 /
b10000 #
b10000 -
b10000 ,
b10011 +
b1101 .
b10011 1
b100011 )
b100011 >
b11010 9
b10100 8
b110011001100110011001100110100 :
b10011 7
b10011 %
b10011 (
b10011 5
1&
1$
#200000
0$
#205000
b1001101 0
b1001101 /
b101100 7
b10011 8
b110000101000111101011100001011 :
b10100 9
b11010 )
b11010 >
b10100 +
b1010 .
b101100 1
b110011 #
b110011 -
b110011 ,
b101100 %
b101100 (
b101100 5
0&
1$
#210000
0$
#215000
b111001 /
b111001 0
b1001101 #
b1001101 -
b1001101 ,
b10101 +
b100 .
b11011 1
b10100 )
b10100 >
b10011 9
b101100 8
b1110000101000111101011100001100 :
b11011 7
b11011 %
b11011 (
b11011 5
1$
#220000
0$
#225000
b1001100 0
b1001100 /
b1010 7
b11011 8
b1000101000111101011100001010011 :
b101100 9
b10011 )
b10011 >
b10110 +
b1001 .
b1010 1
b111001 #
b111001 -
b111001 ,
b1010 %
b1010 (
b1010 5
1&
1$
#230000
0$
#235000
b100000 /
b100000 0
b1001100 #
b1001100 -
b1001100 ,
b10111 +
b10 .
b1110 1
b101100 )
b101100 >
b11011 9
b1010 8
b11001100110011001100110011010 :
b1110 7
b1110 %
b1110 (
b1110 5
0&
1$
#240000
0$
#245000
b101 /
b101 0
b101011 7
b1110 8
b100011110101110000101000111110 :
b1010 9
b11011 )
b11011 >
b11000 +
b101 .
b101011 1
b100000 #
b100000 -
b100000 ,
b101011 %
b101011 (
b101011 5
1&
1$
#250000
0$
#255000
b1111 0
b1111 /
b101 #
b101 -
b101 ,
b11001 +
b1011 .
b100011 1
b1010 )
b1010 >
b1110 9
b101011 8
b1101110000101000111101011100011 :
b100011 7
b100011 %
b100011 (
b100011 5
1$
#260000
0$
#265000
b1 /
b1 0
b11001 7
b100011 8
b1011001100110011001100110011011 :
b101011 9
b1110 )
b1110 >
b11010 +
b110 .
b11001 1
b1111 #
b1111 -
b1111 ,
b11001 %
b11001 (
b11001 5
0&
1$
#270000
0$
#275000
b101100 0
b101100 /
b1 #
b1 -
b1 ,
b11011 +
b1100 .
b100011 1
b101011 )
b101011 >
b100011 9
b11001 8
b1000000000000000000000000000001 :
b100011 7
b100011 %
b100011 (
b100011 5
1$
#280000
0$
#285000
b1001111 0
b1001111 /
b1 7
b100011 8
b1011001100110011001100110011011 :
b11001 9
b100011 )
b100011 >
b11100 +
b1000 .
b1 1
b101100 #
b101100 -
b101100 ,
b1 %
b1 (
b1 5
1$
#290000
0$
#295000
b110110 /
b110110 0
b1001111 #
b1001111 -
b1001111 ,
b11101 +
b1 .
b100010 1
b11001 )
b11001 >
b100011 9
b1 8
b10100011110101110000101001 :
b100010 7
b100010 %
b100010 (
b100010 5
1&
1$
#300000
0$
#305000
b10011 /
b10011 0
b11 7
b100010 8
b1010111000010100011110101110010 :
b1 9
b100011 )
b100011 >
b11110 +
b10 .
b11 1
b110110 #
b110110 -
b110110 ,
b11 %
b11 (
b11 5
0&
1$
#310000
0$
#315000
b10010 /
b10010 0
b10011 #
b10011 -
b10011 ,
b11111 +
b101 .
b11001 1
b1 )
b1 >
b100010 9
b11 8
b111101011100001010001111011 :
b11001 7
b11001 %
b11001 (
b11001 5
1&
1$
#320000
0$
#325000
b110100 0
b110100 /
b111 7
b11001 8
b1000000000000000000000000000001 :
b11 9
b100010 )
b100010 >
b100000 +
b1011 .
b111 1
b10010 #
b10010 -
b10010 ,
b111 %
b111 (
b111 5
1$
#330000
0$
#335000
b110001 /
b110001 0
b110100 #
b110100 -
b110100 ,
b100001 +
b110 .
b101100 1
b11 )
b11 >
b11001 9
b111 8
b10001111010111000010100011111 :
b101100 7
b101100 %
b101100 (
b101100 5
0&
1$
#340000
0$
#345000
b1001010 0
b1001010 /
b1011 7
b101100 8
b1110000101000111101011100001100 :
b111 9
b11001 )
b11001 >
b100010 +
b1101 .
b1011 1
b110001 #
b110001 -
b110001 ,
b1011 %
b1011 (
b1011 5
1&
1$
#350000
0$
#355000
b1010001 0
b1010001 /
b1001010 #
b1001010 -
b1001010 ,
b100011 +
b1010 .
b10111 1
b111 )
b111 >
b101100 9
b1011 8
b11100001010001111010111000011 :
b10111 7
b10111 %
b10111 (
b10111 5
0&
1$
#360000
0$
#365000
b100101 /
b100101 0
b10110 7
b10111 8
b111010111000010100011110101111 :
b1011 9
b101100 )
b101100 >
b100100 +
b101 .
b10110 1
b1010001 #
b1010001 -
b1010001 ,
b10110 %
b10110 (
b10110 5
1&
1$
#370000
0$
#375000
b110000 0
b110000 /
b100101 #
b100101 -
b100101 ,
b100101 +
b1010 .
b10011 1
b1011 )
b1011 >
b10111 9
b10110 8
b111000010100011110101110000110 :
b10011 7
b10011 %
b10011 (
b10011 5
0&
1$
#380000
0$
#385000
b11001 /
b11001 0
b100111 7
b10011 8
b110000101000111101011100001011 :
b10110 9
b10111 )
b10111 >
b100110 +
b100 .
b100111 1
b110000 #
b110000 -
b110000 ,
b100111 %
b100111 (
b100111 5
1$
#390000
0$
#395000
b101111 0
b101111 /
b11001 #
b11001 -
b11001 ,
b100111 +
b1000 .
b11000 1
b10110 )
b10110 >
b10011 9
b100111 8
b1100011110101110000101000111111 :
b11000 7
b11000 %
b11000 (
b11000 5
1$
#400000
0$
#405000
b11100 /
b11100 0
b110010 7
b11000 8
b111101011100001010001111011000 :
b100111 9
b10011 )
b10011 >
b101000 +
b0 .
b110010 1
b101111 #
b101111 -
b101111 ,
b110010 %
b110010 (
b110010 5
1$
#410000
0$
#415000
13
b1011001 /
b111110101 0
b11100 #
b11100 -
b11100 ,
b101001 +
b1 .
b11110 1
b100111 )
b100111 >
b11000 9
b110010 8
b10000000000000000000000000000010 :
b11110 7
b11110 %
b11110 (
b11110 5
1&
1$
#420000
0$
#425000
03
b1000001 /
b1000001 0
b101010 7
b11110 8
b1001100110011001100110011001110 :
b110010 9
b11000 )
b11000 >
b101010 +
b11 .
b101010 1
b100 !
b100 4
b1011001 #
b1011001 -
b1011001 ,
b101010 %
b101010 (
b101010 5
1$
#430000
0$
#435000
b1111 /
b1111 0
b1000001 #
b1000001 -
b1000001 ,
b101011 +
b111 .
b100111 1
b110010 )
b110010 >
b11110 9
b101010 8
b1101011100001010001111010111010 :
b100111 7
b100111 %
b100111 (
b100111 5
1$
#440000
0$
#445000
b101101 0
b101101 /
b11110 7
b100111 8
b1100011110101110000101000111111 :
b101010 9
b11110 )
b11110 >
b101100 +
b1111 .
b11110 1
b1111 #
b1111 -
b1111 ,
b11110 %
b11110 (
b11110 5
1$
#450000
0$
#455000
b1010111 0
b1010111 /
b101101 #
b101101 -
b101101 ,
b101101 +
b1001 1
b101010 )
b101010 >
b100111 9
b11110 8
b1001100110011001100110011001110 :
b1001 7
b1001 %
b1001 (
b1001 5
1$
#460000
0$
#465000
13
b1111110 0
b11010 /
b101110 7
b1001 8
b10111000010100011110101110001 :
b11110 9
b100111 )
b100111 >
b101110 +
b1110 .
b101110 1
b1010111 #
b1010111 -
b1010111 ,
b101110 %
b101110 (
b101110 5
0&
1$
#470000
0$
#475000
03
b111000 0
b111000 /
b101 !
b101 4
b11010 #
b11010 -
b11010 ,
b101111 +
b1101 .
b101101 1
b11110 )
b11110 >
b1001 9
b101110 8
b1110101110000101000111101011110 :
b101101 7
b101101 %
b101101 (
b101101 5
1&
1$
#480000
0$
#485000
b1000001 0
b1000001 /
b100000 7
b101101 8
b1110011001100110011001100110101 :
b101110 9
b1001 )
b1001 >
b110000 +
b1010 .
b100000 1
b111000 #
b111000 -
b111000 ,
b100000 %
b100000 (
b100000 5
0&
1$
#490000
0$
#495000
b10011 /
b10011 0
b1000001 #
b1000001 -
b1000001 ,
b110001 +
b101 .
b10110 1
b101110 )
b101110 >
b101101 9
b100000 8
b1010001111010111000010100100000 :
b10110 7
b10110 %
b10110 (
b10110 5
1&
1$
#500000
0$
#505000
b1000000 0
b1000000 /
b100011 7
b10110 8
b111000010100011110101110000110 :
b100000 9
b101101 )
b101101 >
b110010 +
b1011 .
b100011 1
b10011 #
b10011 -
b10011 ,
b100011 %
b100011 (
b100011 5
1$
#510000
0$
#515000
b100000 /
b100000 0
b1000000 #
b1000000 -
b1000000 ,
b110011 +
b111 .
b1011 1
b100000 )
b100000 >
b10110 9
b100011 8
b1011001100110011001100110011011 :
b1011 7
b1011 %
b1011 (
b1011 5
1$
#520000
0$
#525000
b110110 0
b110110 /
b100000 7
b1011 8
b11100001010001111010111000011 :
b100011 9
b10110 )
b10110 >
b110100 +
b1110 .
b100000 1
b100000 #
b100000 -
b100000 ,
b100000 %
b100000 (
b100000 5
0&
1$
#530000
0$
#535000
b1011001 0
b1011001 /
b110110 #
b110110 -
b110110 ,
b110101 +
b1101 .
b100011 )
b100011 >
b1011 9
b100000 8
b1010001111010111000010100100000 :
1&
1$
#540000
0$
#545000
b1100100 0
b0 /
b1010110 7
b100000 9
b1011 )
b1011 >
b110110 +
b1011 .
b1010110 1
b1011001 #
b1011001 -
b1011001 ,
b1010110 %
b1010110 (
b1010110 5
1$
#550000
0$
#555000
b1000100 /
b111100000 0
b1 "
b1 2
b0 #
b0 -
b0 ,
b110111 +
b110 .
b1000011 1
b100000 )
b100000 >
b1010110 8
b11011100001010001111010111000110 :
b1000011 7
b1000011 %
b1000011 (
b1000011 5
0&
1$
#560000
0$
#565000
b1100100 0
b0 /
b1001 7
b1000011 8
b10101011100001010001111010111011 :
b1010110 9
b111000 +
b1100 .
b1001 1
b1000100 #
b1000100 -
b1000100 ,
b1001 %
b1001 (
b1001 5
1$
#570000
0$
#575000
b1010110 0
b1010110 /
b10 "
b10 2
b0 #
b0 -
b0 ,
b111001 +
b1000 .
b100010 1
b1010110 )
b1010110 >
b1000011 9
b1001 8
b10111000010100011110101110001 :
b100010 7
b100010 %
b100010 (
b100010 5
1$
#580000
0$
#585000
b10011 /
b10011 0
b11000 7
b100010 8
b1010111000010100011110101110010 :
b1001 9
b1000011 )
b1000011 >
b111010 +
b1 .
b11000 1
b1010110 #
b1010110 -
b1010110 ,
b11000 %
b11000 (
b11000 5
1&
1$
#590000
0$
#595000
b1010 /
b1010 0
b10011 #
b10011 -
b10011 ,
b111011 +
b11 .
b1000010 1
b1001 )
b1001 >
b100010 9
b11000 8
b111101011100001010001111011000 :
b1000010 7
b1000010 %
b1000010 (
b1000010 5
1$
#600000
0$
#605000
13
b1001100 /
b111101000 0
b100010 7
b1000010 8
b10101000111101011100001010010010 :
b11000 9
b100010 )
b100010 >
b111100 +
b111 .
b100010 1
b1010 #
b1010 -
b1010 ,
b100010 %
b100010 (
b100010 5
1$
#610000
0$
#615000
03
b1100100 0
b0 /
b110 !
b110 4
b1001100 #
b1001100 -
b1001100 ,
b111101 +
b1111 .
b100110 1
b11000 )
b11000 >
b1000010 9
b100010 8
b1010111000010100011110101110010 :
b100110 7
b100110 %
b100110 (
b100110 5
1$
#620000
0$
#625000
b1000010 0
b1000010 /
b100001 7
b100110 8
b1100001010001111010111000010110 :
b100010 9
b1000010 )
b1000010 >
b111110 +
b100001 1
b11 "
b11 2
b0 #
b0 -
b0 ,
b100001 %
b100001 (
b100001 5
1$
#630000
0$
#635000
b1100100 0
b0 /
b1000010 #
b1000010 -
b1000010 ,
b111111 +
b1110 .
b1000111 1
b100010 )
b100010 >
b100110 9
b100001 8
b1010100011110101110000101001001 :
b1000111 7
b1000111 %
b1000111 (
b1000111 5
0&
1$
#640000
0$
#645000
b100110 0
b100110 /
b1001 7
b1000111 8
b10110101110000101000111101011111 :
b100001 9
b100110 )
b100110 >
b1000000 +
b1101 .
b1001 1
b100 "
b100 2
b0 #
b0 -
b0 ,
b1001 %
b1001 (
b1001 5
1&
1$
#650000
0$
#655000
b1000111 0
b1000111 /
b100110 #
b100110 -
b100110 ,
b1000001 +
b1011 .
b1011011 1
b100001 )
b100001 >
b1000111 9
b1001 8
b10111000010100011110101110001 :
b1011011 7
b1011011 %
b1011011 (
b1011011 5
1$
#660000
0$
#665000
b0 /
b0 0
b10011 7
b1011011 8
b11101000111101011100001010010011 :
b1001 9
b1000111 )
b1000111 >
b1000010 +
b111 .
b10011 1
b1000111 #
b1000111 -
b1000111 ,
b10011 %
b10011 (
b10011 5
1$
#670000
0$
#675000
b1001 0
b1001 /
b101 "
b101 2
b0 #
b0 -
b0 ,
b1000011 +
b1111 .
b1010001 1
b1001 )
b1001 >
b1011011 9
b10011 8
b110000101000111101011100001011 :
b1010001 7
b1010001 %
b1010001 (
b1010001 5
1$
#680000
0$
#685000
b1100100 0
b0 /
b1000000 7
b1010001 8
b11001111010111000010100011111001 :
b10011 9
b1011011 )
b1011011 >
b1000100 +
b1000000 1
b1001 #
b1001 -
b1001 ,
b1000000 %
b1000000 (
b1000000 5
1$
#690000
0$
#695000
b10011 0
b10011 /
b110 "
b110 2
b0 #
b0 -
b0 ,
b1000101 +
b100100 1
b10011 )
b10011 >
b1010001 9
b1000000 8
b10100011110101110000101001000000 :
b100100 7
b100100 %
b100100 (
b100100 5
1$
#700000
0$
#705000
b1100100 0
b0 /
b1011 7
b100100 8
b1011100001010001111010111000100 :
b1000000 9
b1010001 )
b1010001 >
b1000110 +
b1011 1
b10011 #
b10011 -
b10011 ,
b1011 %
b1011 (
b1011 5
1$
#710000
0$
#715000
b1000000 0
b1000000 /
b111 "
b111 2
b0 #
b0 -
b0 ,
b1000111 +
b10 1
b1000000 )
b1000000 >
b100100 9
b1011 8
b11100001010001111010111000011 :
b10 7
b10 %
b10 (
b10 5
1$
#720000
0$
#725000
b1100100 0
b0 /
b101101 7
b10 8
b101000111101011100001010010 :
b1011 9
b100100 )
b100100 >
b1001000 +
b1110 .
b101101 1
b1000000 #
b1000000 -
b1000000 ,
b101101 %
b101101 (
b101101 5
0&
1$
#730000
0$
#735000
b1011 0
b1011 /
b1000 "
b1000 2
b0 #
b0 -
b0 ,
b1001001 +
b1100 .
b1000100 1
b1011 )
b1011 >
b10 9
b101101 8
b1110011001100110011001100110101 :
b1000100 7
b1000100 %
b1000100 (
b1000100 5
1$
#740000
0$
#745000
b1101 0
b1101 /
b11011 7
b1000100 8
b10101110000101000111101011100100 :
b101101 9
b10 )
b10 >
b1001010 +
b1000 .
b11011 1
b1011 #
b1011 -
b1011 ,
b11011 %
b11011 (
b11011 5
1$
#750000
0$
#755000
13
b1000100 /
b111100000 0
b1101 #
b1101 -
b1101 ,
b1001011 +
b0 .
b1011 1
b101101 )
b101101 >
b1000100 9
b11011 8
b1000101000111101011100001010011 :
b1011 7
b1011 %
b1011 (
b1011 5
1$
#760000
0$
#765000
03
b0 /
b0 0
b11011 7
b1011 8
b11100001010001111010111000011 :
b11011 9
b1000100 )
b1000100 >
b1001100 +
b11011 1
b111 !
b111 4
b1000100 #
b1000100 -
b1000100 ,
b11011 %
b11011 (
b11011 5
1$
#770000
0$
#775000
b1001001 /
b111100101 0
b1001 "
b1001 2
b0 #
b0 -
b0 ,
b1001101 +
b100011 1
b11011 )
b11011 >
b1011 9
b11011 8
b1000101000111101011100001010011 :
b100011 7
b100011 %
b100011 (
b100011 5
1$
#780000
0$
#785000
b111110 /
b111110 0
b1100000 7
b100011 8
b1011001100110011001100110011011 :
b11011 9
b1011 )
b1011 >
b1001110 +
b1100000 1
b1001001 #
b1001001 -
b1001001 ,
b1100000 %
b1100000 (
b1100000 5
1$
#790000
0$
#795000
b100011 /
b100011 0
b111110 #
b111110 -
b111110 ,
b1001111 +
b1 .
b101001 1
b11011 )
b11011 >
b100011 9
b1100000 8
b11110101110000101000111101100000 :
b101001 7
b101001 %
b101001 (
b101001 5
1&
1$
#800000
0$
#805000
b0 /
b0 0
b110111 7
b101001 8
b1101000111101011100001010010001 :
b1100000 9
b100011 )
b100011 >
b1010000 +
b11 .
b110111 1
b100011 #
b100011 -
b100011 ,
b110111 %
b110111 (
b110111 5
1$
#810000
0$
#815000
b100 /
b110100000 0
b1010 "
b1010 2
b0 #
b0 -
b0 ,
b1010001 +
b111 .
b1011101 1
b1100000 )
b1100000 >
b101001 9
b110111 8
b10001100110011001100110011001111 :
b1011101 7
b1011101 %
b1011101 (
b1011101 5
1$
#820000
0$
#825000
b101101 0
b101101 /
b1011101 8
b11101110000101000111101011100101 :
b110111 9
b101001 )
b101001 >
b1010010 +
b1110 .
b100 #
b100 -
b100 ,
0&
1$
#830000
0$
#835000
b1100100 0
b0 /
b101101 #
b101101 -
b101101 ,
b1010011 +
b1100 .
b1000 1
b110111 )
b110111 >
b1011101 9
b1000 7
b1000 %
b1000 (
b1000 5
1$
#840000
0$
#845000
b1011101 0
b1011101 /
b1011100 7
b1000 8
b10100011110101110000101001000 :
b1011101 )
b1011101 >
b1010100 +
b1000 .
b1011100 1
b1011 "
b1011 2
b0 #
b0 -
b0 ,
b1011100 %
b1011100 (
b1011100 5
1$
#850000
0$
#855000
b0 /
b0 0
b1011101 #
b1011101 -
b1011101 ,
b1010101 +
b0 .
b10000 1
b1000 9
b1011100 8
b11101011100001010001111010111100 :
b10000 7
b10000 %
b10000 (
b10000 5
1$
#860000
0$
#865000
b1011100 /
b111111000 0
b10000 8
b101000111101011100001010010000 :
b1011100 9
b1000 )
b1000 >
b1010110 +
b1 .
b1100 "
b1100 2
b0 #
b0 -
b0 ,
1&
1$
#870000
0$
#875000
b0 /
b0 0
b1011100 #
b1011100 -
b1011100 ,
b1010111 +
b11 .
b101010 1
b1011100 )
b1011100 >
b10000 9
b101010 7
b101010 %
b101010 (
b101010 5
1$
#880000
0$
#885000
b1010100 /
b111110000 0
b110110 7
b101010 8
b1101011100001010001111010111010 :
b10000 )
b10000 >
b1011000 +
b111 .
b110110 1
b1101 "
b1101 2
b0 #
b0 -
b0 ,
b110110 %
b110110 (
b110110 5
1$
#890000
0$
#895000
b1100100 0
b0 /
b1010100 #
b1010100 -
b1010100 ,
b1011001 +
b1110 .
b1010 1
b101010 9
b110110 8
b10001010001111010111000010100110 :
b1010 7
b1010 %
b1010 (
b1010 5
0&
1$
#900000
0$
