day-1/day1-verilog/src/mod100_pipelined.v
module mod100_pipelined (
    input  wire        clk,
    input  wire        rst,
    input  wire [31:0] in_data,
    output reg  [7:0]  rot_by  // valid 3 cycles after input
);

    // constant = floor(2^32 / 100) = magic number for fast division
    localparam MAGIC = 32'd42949673;

    // ---------------- Pipeline Registers ----------------
    reg [31:0] in_s0;      // stage 0: input latch

    reg [63:0] mult_s1;    // stage 1: multiplication
    reg [31:0] in_s1;

    reg [31:0] q_s2;       // stage 2: quotient
    reg [31:0] in_s2;

    reg [31:0] r_s3;       // stage 3: remainder

    // ---------------- Stage 0 ----------------
    always @(posedge clk or posedge rst) begin
        if (rst)
            in_s0 <= 0;
        else
            in_s0 <= in_data;
    end

    // ---------------- Stage 1 ----------------
    always @(posedge clk or posedge rst) begin
        if (rst) begin
            mult_s1 <= 0;
            in_s1   <= 0;
        end else begin
            mult_s1 <= in_s0 * MAGIC;   // 64-bit product
            in_s1   <= in_s0;
        end
    end

    // ---------------- Stage 2 ----------------
    always @(posedge clk or posedge rst) begin
        if (rst) begin
            q_s2 <= 0;
            in_s2 <= 0;
        end else begin
            q_s2 <= mult_s1 >> 32;      // approximate quotient
            in_s2 <= in_s1;
        end
    end

    // ---------------- Stage 3 ----------------
    always @(posedge clk or posedge rst) begin
        if (rst) begin
            r_s3   <= 0;
            rot_by <= 0;
        end else begin
            // compute remainder
            r_s3   <= in_s2 - (q_s2 * 32'd100);

            // FULLY SAFE BOUNDS — ENSURE < 100
            if (r_s3 >= 100)
                rot_by <= r_s3 - 100;
            else
                rot_by <= r_s3[7:0];
        end
    end

endmodule

day-1/day1-verilog/src/sol.v
module aoc_day1(
    input  wire [31:0] in_data,
    input  wire        clk,
    input  wire        rst,
    input  wire        dir_r,
    output reg  [31:0] zero_count
);

    wire [7:0] rot_by;  // modulo result after 3 cycles

    mod100_pipelined mod_unit (
        .clk(clk),
        .rst(rst),
        .in_data(in_data),
        .rot_by(rot_by)
    );

    reg [7:0]  curr_pos = 8'd50;
    reg [31:0] zero_count_int;

    // local combinational next state
    reg [9:0] temp_pos_next;
    reg [7:0] curr_pos_next;

    always @(*) begin
        // compute next position based on rot_by
        if (dir_r) begin
            temp_pos_next = curr_pos + rot_by;
            if (temp_pos_next >= 10'd100)
                curr_pos_next = temp_pos_next - 10'd100;
            else
                curr_pos_next = temp_pos_next[7:0];
        end else begin
            temp_pos_next = curr_pos + (8'd100 - rot_by);
            if (temp_pos_next >= 10'd100)
                curr_pos_next = temp_pos_next - 10'd100;
            else
                curr_pos_next = temp_pos_next[7:0];
        end
    end

    always @(posedge clk or posedge rst) begin
        if (rst) begin
            curr_pos       <= 8'd50;
            zero_count_int <= 0;
            zero_count     <= 0;
        end else begin
            curr_pos <= curr_pos_next;

            if (curr_pos_next == 0)
                zero_count_int <= zero_count_int + 1;

            zero_count <= zero_count_int;
        end
    end

endmodule

day-1/verilog/src/testbenches/sol_test/sol_tb_test.v
`timescale 1ns / 1ps

module aoc_day1_tb_test();

    // Instantiate DUT inputs
    reg  [31:0] data_in = 32'b0;
    reg         clk     = 1'b0;
    reg         rst     = 1'b0;
    reg         dir_r   = 1'b0;

    wire [31:0] zero_count;

    // Instantiate DUT
    aoc_day1 uut (
        .in_data(data_in),
        .clk(clk),
        .rst(rst),
        .dir_r(dir_r),
        .zero_count(zero_count)
    );

    // Clock generation: 10ns period
    always #5 clk = ~clk;

    initial begin
        // VCD DUMP
        $dumpfile("aoc_day1_test.vcd");
        $dumpvars(0, aoc_day1_tb_test);

        // Reset sequence
        @(posedge clk);
        rst     = 1;
        data_in = 0;
        dir_r   = 0;

        @(posedge clk);
        rst = 0;

        // Apply test vectors
        @(posedge clk); dir_r = 0; data_in = 68;
        @(posedge clk); dir_r = 0; data_in = 30;
        @(posedge clk); dir_r = 1; data_in = 48;
        @(posedge clk); dir_r = 0; data_in = 5;
        @(posedge clk); dir_r = 1; data_in = 60;
        @(posedge clk); dir_r = 0; data_in = 55;
        @(posedge clk); dir_r = 0; data_in = 1;
        @(posedge clk); dir_r = 0; data_in = 99;
        @(posedge clk); dir_r = 1; data_in = 14;
        @(posedge clk); dir_r = 0; data_in = 82;

        // Allow pipeline to flush
        repeat (10) @(posedge clk);

        $display("Simulation Ended. Final Zero Count = %0d", zero_count);
        $finish;
    end

endmodule

day-1/day1-verilog/src/testbenches/aoc_day1_test.vcd
$date
	Sat Dec  6 18:59:23 2025
$end
$version
	Icarus Verilog
$end
$timescale
	1ps
$end
$scope module aoc_day1_tb_test $end
$var wire 32 ! zero_count [31:0] $end
$var reg 1 " clk $end
$var reg 32 # data_in [31:0] $end
$var reg 1 $ dir_r $end
$var reg 1 % rst $end
$scope module uut $end
$var wire 1 " clk $end
$var wire 1 $ dir_r $end
$var wire 32 & in_data [31:0] $end
$var wire 1 % rst $end
$var wire 8 ' rot_by [7:0] $end
$var reg 8 ( curr_pos [7:0] $end
$var reg 8 ) curr_pos_next [7:0] $end
$var reg 10 * temp_pos_next [9:0] $end
$var reg 32 + zero_count [31:0] $end
$var reg 32 , zero_count_int [31:0] $end
$scope module mod_unit $end
$var wire 1 " clk $end
$var wire 32 - in_data [31:0] $end
$var wire 1 % rst $end
$var parameter 32 . MAGIC $end
$var reg 32 / in_s0 [31:0] $end
$var reg 32 0 in_s1 [31:0] $end
$var reg 32 1 in_s2 [31:0] $end
$var reg 64 2 mult_s1 [63:0] $end
$var reg 32 3 q_s2 [31:0] $end
$var reg 32 4 r_s3 [31:0] $end
$var reg 8 5 rot_by [7:0] $end
$upscope $end
$upscope $end
$upscope $end
$enddefinitions $end
$comment Show the parameter values. $end
$dumpall
b10100011110101110000101001 .
$end
#0
$dumpvars
bx 5
bx 4
bx 3
bx 2
bx 1
bx 0
bx /
b0 -
bx ,
bx +
bx *
bx )
b110010 (
bx '
b0 &
0%
0$
b0 #
0"
bx !
$end
#5000
b110010 )
b10010110 *
b0 /
b0 0
b0 2
b0 1
b0 3
b0 '
b0 5
b0 4
b0 !
b0 +
b0 ,
1%
1"
#10000
0"
#15000
0%
1"
#20000
0"
#25000
b1000100 /
b1000100 #
b1000100 &
b1000100 -
1"
#30000
0"
#35000
b1000100 0
b10101110000101000111101011100100 2
b11110 /
b11110 #
b11110 &
b11110 -
1"
#40000
0"
#45000
b110000 /
b11110 0
b1001100110011001100110011001110 2
b1000100 1
b110010 *
b110000 #
b110000 &
b110000 -
1$
1"
#50000
0"
#55000
b1000100 4
b11110 1
b110000 0
b1111010111000010100011110110000 2
b101 /
b10010110 *
b101 #
b101 &
b101 -
0$
1"
#60000
0"
#65000
b10010 )
b111100 /
b101 0
b1100110011001100110011001101 2
b110000 1
b1000100 '
b1000100 5
b11110 4
b1110110 *
b111100 #
b111100 &
b111100 -
1$
1"
#70000
0"
#75000
b10010 (
b11110 '
b11110 5
b110000 4
b101 1
b111100 0
b10011001100110011001100110011100 2
b110111 /
b1011000 )
b1011000 *
b110111 #
b110111 &
b110111 -
0$
1"
#80000
0"
#85000
b101000 )
b10001100 *
b1 /
b110111 0
b10001100110011001100110011001111 2
b111100 1
b110000 '
b110000 5
b101 4
b1011000 (
b1 #
b1 &
b1 -
1"
#90000
0"
#95000
b100011 )
b10000111 *
b101000 (
b101 '
b101 5
b111100 4
b110111 1
b1 0
b10100011110101110000101001 2
b1100011 /
b1100011 #
b1100011 &
b1100011 -
1"
#100000
0"
#105000
b1110 /
b1100011 0
b11111101011100001010001111011011 2
b1 1
b111100 '
b111100 5
b110111 4
b100011 (
b1011111 )
b1011111 *
b1110 #
b1110 &
b1110 -
1$
1"
#110000
0"
#115000
b1011111 (
b110111 '
b110111 5
b1 4
b1100011 1
b1110 0
b100011110101110000101000111110 2
b1010010 /
b101000 )
b10001100 *
b1010010 #
b1010010 &
b1010010 -
0$
1"
#120000
0"
#125000
b100111 )
b10001011 *
b1010010 0
b11010001111010111000010100100010 2
b1110 1
b1 '
b1 5
b1100011 4
b101000 (
1"
#130000
0"
#135000
b101000 )
b101000 *
b100111 (
b1100011 '
b1100011 5
b1110 4
b1010010 1
1"
#140000
0"
#145000
b11010 )
b1111110 *
b1110 '
b1110 5
b1010010 4
b101000 (
1"
#150000
0"
#155000
b101100 )
b101100 *
b11010 (
b1010010 '
b1010010 5
1"
#160000
0"
#165000
b111110 )
b111110 *
b101100 (
1"
#170000
0"
#175000
b1010000 )
b1010000 *
b111110 (
1"
#180000
0"
#185000
b1100010 )
b1100010 *
b1010000 (
1"
#190000
0"
#195000
b10000 )
b1110100 *
b1100010 (
1"
#200000
0"
#205000
b100010 )
b100010 *
b10000 (
1"
#210000
0"
#215000
b110100 )
b110100 *
b100010 (
1"
