day-1/verilog-implementation/rtl/sol.v
module aoc_day1(
    input wire  [31:0] in_data,
    input wire  clk,
    input wire  rst,
    input wire  dir_r,
    output reg [31:0] zero_count 
);

    //Modulo must be synthesizable, so we need some magic.
    localparam DIV100_MOD_CONST = 32'd42949673; // floor(2^32 / 100)
    reg [63:0] mult = 64'b0;
    reg [31:0] q = 32'b0;
    reg [31:0] r = 32'b0;

    //FIFO of width 32 and depth 4 required to hold

    reg [9:0] temp_pos = 8'd50;
    reg [7:0] curr_pos = 8'd50;
    reg [31:0] zero_count_int = 32'd0;

    reg [7:0] rot_by;
    always @(posedge clk or posedge rst) begin
        if(rst) begin
            curr_pos = 8'd0;
            zero_count = 16'd0;
        end
        else begin
            mult = in_data * DIV100_MOD_CONST;
            q = mult >> 32;
            r = in_data - q * 8'd100;
            rot_by = r[7:0];
            if(dir_r) begin
                temp_pos = (curr_pos + rot_by);
                if(temp_pos >= 8'd100) begin
                    curr_pos = temp_pos - 8'd100;
                end
                else begin
                    curr_pos = temp_pos;
                end
            end
            else begin
                temp_pos = (curr_pos + (100 - rot_by));
                if(temp_pos >= 8'd100) begin
                    curr_pos = temp_pos - 8'd100;  
                end
            end
        end
        if(curr_pos == 8'd0) begin
            zero_count_int = zero_count_int + 1;
        end
        zero_count = zero_count_int;
    end
endmodule

day-1/verilog-implementation/rtl/sol_tb_test.v
`timescale 1ns / 1ps

module aoc_day1_tb();

    //Insantiating the module
    reg [31:0] data_in = 32'b0;
    reg clk = 1'b0;
    reg rst = 1'b0;
    reg dir_r = 1'b0;
    wire [31:0] zero_count;

    aoc_day1 uut(
        .in_data(data_in),
        .clk(clk),
        .rst(rst),
        .dir_r(dir_r),
        .zero_count(zero_count)
    );

    //Clock generation
    initial clk = 0;
    always #5 clk = ~clk; // 10 time units clock period

    initial begin
        $dumpfile("aoc_day1_test.vcd");
        $dumpvars(0, aoc_day1_tb);
        
        @(posedge clk)
        rst = 1;
        data_in = 32'b0;
        dir_r = 1'b0;

        @(posedge clk)
        rst = 0;

        //Now the actual data
        @(posedge clk); dir_r = 0; data_in = 68;
        @(posedge clk); dir_r = 0; data_in = 30;
        @(posedge clk); dir_r = 1; data_in = 48;
        @(posedge clk); dir_r = 0; data_in = 5;
        @(posedge clk); dir_r = 1; data_in = 60;
        @(posedge clk); dir_r = 0; data_in = 55;
        @(posedge clk); dir_r = 0; data_in = 1;
        @(posedge clk); dir_r = 0; data_in = 99;
        @(posedge clk); dir_r = 1; data_in = 14;
        @(posedge clk); dir_r = 0; data_in = 82;

        //Ending the simulation
        repeat(3) @(posedge clk);
        $display("Simulation Ended. Final Zero Count = %0d", zero_count);

        $finish;
    end

endmodule

day-1/verilog-implementation/rtl/aoc_day1_test.vcd
$date
	Sat Dec  6 11:05:18 2025
$end
$version
	Icarus Verilog
$end
$timescale
	1ps
$end
$scope module aoc_day1_tb $end
$var wire 32 ! zero_count [31:0] $end
$var reg 1 " clk $end
$var reg 32 # data_in [31:0] $end
$var reg 1 $ dir_r $end
$var reg 1 % rst $end
$scope module uut $end
$var wire 1 " clk $end
$var wire 1 $ dir_r $end
$var wire 32 & in_data [31:0] $end
$var wire 1 % rst $end
$var parameter 32 ' DIV100_MOD_CONST $end
$var reg 8 ( curr_pos [7:0] $end
$var reg 64 ) mult [63:0] $end
$var reg 32 * q [31:0] $end
$var reg 32 + r [31:0] $end
$var reg 8 , rot_by [7:0] $end
$var reg 10 - temp_pos [9:0] $end
$var reg 32 . zero_count [31:0] $end
$var reg 32 / zero_count_int [31:0] $end
$upscope $end
$upscope $end
$enddefinitions $end
$comment Show the parameter values. $end
$dumpall
b10100011110101110000101001 '
$end
#0
$dumpvars
b0 /
bx .
b110010 -
bx ,
b0 +
b0 *
b0 )
b110010 (
b0 &
0%
0$
b0 #
0"
bx !
$end
#5000
b1 /
b1 !
b1 .
b0 (
1%
1"
#10000
0"
#15000
b10 !
b10 .
b10 /
b1100100 -
b0 ,
0%
1"
#20000
0"
#25000
b11 !
b11 .
b11 /
b100000 -
b1000100 ,
b1000100 +
b10101110000101000111101011100100 )
b1000100 #
b1000100 &
1"
#30000
0"
#35000
b100 !
b100 .
b100 /
b1000110 -
b11110 ,
b11110 +
b1001100110011001100110011001110 )
b11110 #
b11110 &
1"
#40000
0"
#45000
b110000 (
b110000 -
b110000 ,
b110000 +
b1111010111000010100011110110000 )
b110000 #
b110000 &
1$
1"
#50000
0"
#55000
b101011 (
b10001111 -
b101 ,
b101 +
b1100110011001100110011001101 )
b101 #
b101 &
0$
1"
#60000
0"
#65000
b11 (
b1100111 -
b111100 ,
b111100 +
b10011001100110011001100110011100 )
b111100 #
b111100 &
1$
1"
#70000
0"
#75000
b110000 -
b110111 ,
b110111 +
b10001100110011001100110011001111 )
b110111 #
b110111 &
0$
1"
#80000
0"
#85000
b10 (
b1100110 -
b1 ,
b1 +
b10100011110101110000101001 )
b1 #
b1 &
1"
#90000
0"
#95000
b11 -
b1100011 ,
b1100011 +
b11111101011100001010001111011011 )
b1100011 #
b1100011 &
1"
#100000
0"
#105000
b10000 (
b10000 -
b1110 ,
b1110 +
b100011110101110000101000111110 )
b1110 #
b1110 &
1$
1"
#110000
0"
#115000
b100010 -
b1010010 ,
b1010010 +
b11010001111010111000010100100010 )
b1010010 #
b1010010 &
0$
1"
