day-1/verilog-implementation/rtl/sol.v
// zero_counter.v
module zero_counter(
    input  wire [31:0] data_in,
    input  wire        dir_r,
    input  wire        clk,
    input  wire        rst,
    output reg  [15:0] zero_count,   // number of times final pos == 0 (truncated)
    output reg  [15:0] zero_cross    // number of times we crossed position 0 (truncated)
);

    // ----------------------------------------------------------------------------
    // Internal registers (wider for safety)
    // ----------------------------------------------------------------------------
    reg [7:0]  pos;            // current position in 0..99 (use 8 bits)
    reg [31:0] internal_count; // full internal counter for "final pos == 0"
    reg [31:0] internal_cross; // full internal counter for "crossing zero"

    // ----------------------------------------------------------------------------
    // Combinational helpers: rotation decomposition
    // ----------------------------------------------------------------------------
    // full_wraps = data_in / 100  (how many full 0..99 cycles are in data_in)
    // rot_by     = data_in % 100  (remainder rotation within 0..99)
    wire [31:0] full_wraps;
    wire [6:0]  rot_by;          // 0..99 fits in 7 bits
    assign full_wraps = data_in / 100;
    assign rot_by     = data_in % 100;

    // For addition: pos + rot_by may be up to 198 -> use 9 bits to detect >=100
    wire [8:0] sum_add = pos + rot_by;
    wire       add_wrap = (sum_add >= 9'd100);
    wire [6:0] pos_next_add = add_wrap ? (sum_add - 9'd100) : sum_add[6:0];

    // For subtraction: if pos < rot_by, we wrap backwards once (and possibly more via full_wraps)
    wire       sub_wrap = (pos < rot_by);
    wire [6:0] pos_next_sub = sub_wrap ? (pos + 7'd100 - rot_by) : (pos - rot_by);

    // Compute total zero-cross events caused by this rotation:
    // - Each full 100 contributes one crossing.
    // - The remainder (rot_by) contributes at most one extra crossing:
    //   * for forward (dir_r): if add_wrap is true -> +1
    //   * for backward (!dir_r): if sub_wrap is true -> +1
    wire [31:0] extra_wrap_forward = add_wrap ? 32'd1 : 32'd0;
    wire [31:0] extra_wrap_backward = sub_wrap ? 32'd1 : 32'd0;

    // final next-pos (7-bit) depends on direction; compute combinationally
    wire [6:0] next_pos = dir_r ? pos_next_add : pos_next_sub;

    // ----------------------------------------------------------------------------
    // Synchronous update (all non-blocking) — update pos, internal counters and outputs
    // ----------------------------------------------------------------------------
    always @(posedge clk or posedge rst) begin
        if (rst) begin
            pos            = 8'd50;
            internal_count = 32'd0;
            internal_cross = 32'd0;
            zero_count     = 16'd0;
            zero_cross     = 16'd0;
        end else begin
            // Add full_wraps and the possible extra wrap
            if (dir_r) begin
                internal_cross = internal_cross + full_wraps + extra_wrap_forward;
            end else begin
                internal_cross = internal_cross + full_wraps + extra_wrap_backward;
            end

            // Update position (mod 100)
            pos <= {1'b0, next_pos}; // extend to 8 bits safely

            // Update internal_count: increment by 1 if new position equals 0
            if (next_pos == 7'd0)
                internal_count = internal_count + 32'd1;

            // Drive truncated outputs synchronously (lowest 16 bits)
            zero_count = internal_count[15:0];
            zero_cross = internal_cross[15:0];
        end
    end

endmodule

day-1/verilog-implementation/rtl/sol_tb_test.v
`timescale 1ns/1ps

module zero_counter_tb;

    // DUT inputs
    reg  [31:0] data_in;
    reg         dir_r;
    reg         clk;
    reg         rst;

    // DUT output
    wire [15:0] zero_count;
    wire [15:0] zero_cross;

    // Instantiate DUT
    zero_counter dut (
        .data_in(data_in),
        .dir_r(dir_r),
        .clk(clk),
        .rst(rst),
        .zero_count(zero_count),
        .zero_cross(zero_cross)
    );

    // Clock: 10ns period = 100MHz
    always #5 clk = ~clk;

    // MAIN TEST
    initial begin
        // VCD dump for waveforms
        $dumpfile("zero_counter.vcd");
        $dumpvars(0, zero_counter_tb);

        $display("=== ZERO COUNTER TESTBENCH START ===");

        // Initialize signals
        clk     = 0;
        rst     = 0;
        data_in = 0;
        dir_r   = 0;

        // Reset pulse
        rst = 1;
        #20;
        rst = 0;

        // === BEGIN INPUT SEQUENCE ===
        @(posedge clk); dir_r = 0; data_in = 68;
        @(posedge clk); dir_r = 0; data_in = 30;
        @(posedge clk); dir_r = 1; data_in = 48;
        @(posedge clk); dir_r = 0; data_in = 5;
        @(posedge clk); dir_r = 1; data_in = 60;
        @(posedge clk); dir_r = 0; data_in = 55;
        @(posedge clk); dir_r = 0; data_in = 1;
        @(posedge clk); dir_r = 0; data_in = 99;
        @(posedge clk); dir_r = 1; data_in = 14;
        @(posedge clk); dir_r = 0; data_in = 82;
        // === END INPUT SEQUENCE ===

        // Print final result
        #20;
        $display("=== TEST COMPLETE ===");
        $display("Final zero_count = %d", zero_count);
        $display("Final zero_cros = %d", zero_cross);

        $finish;
    end

endmodule

day-1/verilog-implementation/rtl/zero_counter.vcd
$date
	Thu Dec  4 14:24:42 2025
$end
$version
	Icarus Verilog
$end
$timescale
	1ps
$end
$scope module zero_counter_tb $end
$var wire 16 ! zero_cross [15:0] $end
$var wire 16 " zero_count [15:0] $end
$var reg 1 # clk $end
$var reg 32 $ data_in [31:0] $end
$var reg 1 % dir_r $end
$var reg 1 & rst $end
$scope module dut $end
$var wire 1 # clk $end
$var wire 32 ' data_in [31:0] $end
$var wire 1 % dir_r $end
$var wire 1 & rst $end
$var wire 9 ( sum_add [8:0] $end
$var wire 1 ) sub_wrap $end
$var wire 7 * rot_by [6:0] $end
$var wire 7 + pos_next_sub [6:0] $end
$var wire 7 , pos_next_add [6:0] $end
$var wire 7 - next_pos [6:0] $end
$var wire 32 . full_wraps [31:0] $end
$var wire 32 / extra_wrap_forward [31:0] $end
$var wire 32 0 extra_wrap_backward [31:0] $end
$var wire 1 1 add_wrap $end
$var reg 32 2 internal_count [31:0] $end
$var reg 32 3 internal_cross [31:0] $end
$var reg 8 4 pos [7:0] $end
$var reg 16 5 zero_count [15:0] $end
$var reg 16 6 zero_cross [15:0] $end
$upscope $end
$upscope $end
$enddefinitions $end
$comment Show the parameter values. $end
$dumpall
$end
#0
$dumpvars
b0 6
b0 5
b110010 4
b0 3
b0 2
01
b0 0
b0 /
b0 .
b110010 -
b110010 ,
b110010 +
b0 *
0)
b110010 (
b0 '
1&
0%
b0 $
0#
b0 "
b0 !
$end
#5000
1#
#10000
0#
#15000
1#
#20000
0#
0&
#25000
b110111 ,
b101101 -
b101101 +
b110111 (
b101 *
b101 $
b101 '
1#
#30000
0#
#35000
b101101 4
b1010010 ,
b1000 -
b1000 +
b1010010 (
b100101 *
b100101 $
b100101 '
1#
#40000
0#
#45000
b1 0
1)
b1000 4
b101000 ,
b1001100 -
b1001100 +
b101000 (
b100000 *
b100000 $
b100000 '
1#
#50000
0#
#55000
b1001100 4
b1010001 ,
b1000111 +
b0 0
b1010001 (
0)
b101 *
b1010001 -
b101 $
b101 '
1%
1#
#60000
0#
#65000
b1010001 4
b10001 ,
b101101 +
b1 /
11
b1110101 (
b100100 *
b101101 -
b100100 $
b100100 '
0%
1#
#70000
0#
#75000
b0 /
01
b101101 4
b10000 -
b1001010 ,
b10000 +
b1001010 (
b11101 *
b11101 $
b11101 '
1#
#80000
0#
#85000
b10000 4
b11101 ,
b11 +
b11101 (
b1101 *
b11101 -
b1101 $
b1101 '
1%
1#
#90000
0#
#95000
b11101 4
b101110 -
b101110 ,
b1100 +
b0 0
b101110 (
0)
b10001 *
b10001 $
b10001 '
1#
#100000
0#
#105000
b101110 4
b1000001 ,
b11011 +
b1000001 (
b10011 *
b11011 -
b10011 $
b10011 '
0%
1#
#110000
0#
#115000
b1 0
1)
b11011 4
b111101 ,
b1011101 -
b1011101 +
b111101 (
b100010 *
b100010 $
b100010 '
1#
#120000
0#
#125000
b1011101 4
b1011111 ,
b1011011 +
b0 0
b1011111 (
0)
b10 *
b1011111 -
b10 $
b10 '
1%
1#
#130000
0#
#135000
b1011111 4
b100 -
b100 ,
b1010110 +
b1 /
11
b1101000 (
b1001 *
b1001 $
b1001 '
1#
#140000
0#
#145000
b100 4
b101 -
b101 ,
b11 +
b0 /
01
b101 (
b1 *
b1 !
b1 6
b1 3
b1 $
b1 '
1#
#150000
0#
#155000
b101 4
b10000 -
b10000 ,
b1011110 +
b1 0
b10000 (
1)
b1011 *
b1011 $
b1011 '
1#
#160000
0#
#165000
b10000 4
b110011 -
b110011 ,
b1010001 +
b110011 (
b100011 *
b100011 $
b100011 '
1#
#170000
0#
#175000
b0 0
0)
b110011 4
b1001101 -
b1001101 ,
b11001 +
b1001101 (
b11010 *
b11010 $
b11010 '
1#
#180000
0#
#185000
b1001101 4
b1100001 ,
b111001 +
b1100001 (
b10100 *
b111001 -
b10100 $
b10100 '
0%
1#
#190000
0#
#195000
b111001 4
b1001100 ,
b100110 +
b1001100 (
b10011 *
b1001100 -
b10011 $
b10011 '
1%
1#
#200000
0#
#205000
b1001100 4
b10100 ,
b100000 +
b1 /
11
b1111000 (
b101100 *
b100000 -
b101100 $
b101100 '
0%
1#
#210000
0#
#215000
b0 /
01
b100000 4
b101 -
b111011 ,
b101 +
b111011 (
b11011 *
b11011 $
b11011 '
1#
#220000
0#
#225000
b1 0
1)
b101 4
b1111 ,
b1011111 +
b1111 (
b1010 *
b1111 -
b1010 $
b1010 '
1%
1#
#230000
0#
#235000
b0 0
0)
b1111 4
b11101 ,
b1 +
b11101 (
b1110 *
b1 -
b10 !
b10 6
b10 3
b1110 $
b1110 '
0%
1#
#240000
0#
#245000
b1 4
b101100 ,
b111010 +
b1 0
b101100 (
1)
b101011 *
b101100 -
b101011 $
b101011 '
1%
1#
#250000
0#
#255000
b0 0
0)
b101100 4
b1001111 -
b1001111 ,
b1001 +
b1001111 (
b100011 *
b100011 $
b100011 '
1#
#260000
0#
#265000
b1 /
11
b1001111 4
b100 ,
b110110 +
b1101000 (
b11001 *
b110110 -
b11001 $
b11001 '
0%
1#
#270000
0#
#275000
b0 /
01
b110110 4
b10011 -
b1011001 ,
b10011 +
b1011001 (
b100011 *
b100011 $
b100011 '
1#
#280000
0#
#285000
b10011 4
b10100 ,
b10010 -
b10010 +
b10100 (
b1 *
b1 $
b1 '
1#
#290000
0#
#295000
b10010 4
b110100 ,
b1010100 +
b1 0
b110100 (
1)
b100010 *
b110100 -
b100010 $
b100010 '
1%
1#
#300000
0#
#305000
b110100 4
b110111 ,
b110001 +
b0 0
b110111 (
0)
b11 *
b110001 -
b11 !
b11 6
b11 3
b11 $
b11 '
0%
1#
#310000
0#
#315000
b110001 4
b1001010 ,
b11000 +
b1001010 (
b11001 *
b1001010 -
b11001 $
b11001 '
1%
1#
#320000
0#
#325000
b1001010 4
b1010001 -
b1010001 ,
b1000011 +
b1010001 (
b111 *
b111 $
b111 '
1#
#330000
0#
#335000
b1010001 4
b11001 ,
b100101 +
b1 /
11
b1111101 (
b101100 *
b100101 -
b101100 $
b101100 '
0%
1#
#340000
0#
#345000
b100101 4
b110000 ,
b11010 +
b0 /
01
b110000 (
b1011 *
b110000 -
b100 !
b100 6
b100 3
b1011 $
b1011 '
1%
1#
#350000
0#
#355000
b110000 4
b1000111 ,
b11001 +
b1000111 (
b10111 *
b11001 -
b10111 $
b10111 '
0%
1#
#360000
0#
#365000
b11001 4
b101111 ,
b11 +
b101111 (
b10110 *
b101111 -
b10110 $
b10110 '
1%
1#
#370000
0#
#375000
b101111 4
b1000010 ,
b11100 +
b1000010 (
b10011 *
b11100 -
b10011 $
b10011 '
0%
1#
#380000
0#
#385000
b1 0
1)
b11100 4
b1000011 ,
b1011001 -
b1011001 +
b1000011 (
b100111 *
b100111 $
b100111 '
1#
#390000
0#
#395000
b1 /
11
b1011001 4
b1101 ,
b1000001 -
b1000001 +
b0 0
b1110001 (
0)
b11000 *
b101 !
b101 6
b101 3
b11000 $
b11000 '
1#
#400000
0#
#405000
b1000001 4
b1111 -
b1111 ,
b1111 +
b1110011 (
b110010 *
b110010 $
b110010 '
1#
#410000
0#
#415000
b1 0
1)
b1111 4
b101101 -
b101101 ,
b1010101 +
b0 /
01
b101101 (
b11110 *
b110 !
b110 6
b110 3
b11110 $
b11110 '
1%
1#
#420000
0#
#425000
b0 0
0)
b101101 4
b1010111 -
b1010111 ,
b11 +
b1010111 (
b101010 *
b101010 $
b101010 '
1#
#430000
0#
#435000
b1 /
11
b1010111 4
b11010 -
b11010 ,
b110000 +
b1111110 (
b100111 *
b100111 $
b100111 '
1#
#440000
0#
#445000
b0 /
b1 0
01
1)
b11010 4
b111000 -
b111000 ,
b1100000 +
b111000 (
b11110 *
b111 !
b111 6
b111 3
b11110 $
b11110 '
1#
#450000
0#
#455000
b111000 4
b1000001 -
b1000001 ,
b101111 +
b0 0
b1000001 (
0)
b1001 *
b1001 $
b1001 '
1#
#460000
0#
#465000
b1000001 4
b1011 ,
b10011 +
b1 /
11
b1101111 (
b101110 *
b10011 -
b101110 $
b101110 '
0%
1#
#470000
0#
#475000
b0 /
b1 0
01
1)
b10011 4
b1000000 ,
b1001010 +
b1000000 (
b101101 *
b1000000 -
b1000 !
b1000 6
b1000 3
b101101 $
b101101 '
1%
1#
#480000
0#
#485000
b0 0
0)
b1000000 4
b1100000 ,
b100000 +
b1100000 (
b100000 *
b100000 -
b1001 !
b1001 6
b1001 3
b100000 $
b100000 '
0%
1#
#490000
0#
#495000
b100000 4
b110110 ,
b1010 +
b110110 (
b10110 *
b110110 -
b10110 $
b10110 '
1%
1#
#500000
0#
#505000
b110110 4
b1011001 -
b1011001 ,
b10011 +
b0 0
b1011001 (
0)
b100011 *
b100011 $
b100011 '
1#
#510000
0#
#515000
b1 /
11
b1011001 4
b0 -
b0 ,
b1001110 +
b1100100 (
b1011 *
b1011 $
b1011 '
1#
#520000
0#
#525000
b0 /
b1 0
01
1)
b0 4
b100000 ,
b1000100 +
b100000 (
b100000 *
b1000100 -
b1 "
b1 5
b1 2
b100000 $
b100000 '
0%
1#
#530000
0#
#535000
b0 ,
b100100 +
b1 /
b0 0
11
b1100100 (
0)
b1000100 4
b0 -
1%
1#
#540000
0#
#545000
b0 /
01
b0 4
b1010110 -
b1010110 ,
b1110 +
b1 0
b1010110 (
1)
b1010110 *
b1010 !
b1010 6
b10 "
b10 5
b10 2
b1010 3
b1010110 $
b1010110 '
1#
#550000
0#
#555000
b1 /
b0 0
11
0)
b1010110 4
b110101 ,
b10011 +
b10011001 (
b1000011 *
b10011 -
b1011 !
b1011 6
b1011 3
b1000011 $
b1000011 '
0%
1#
#560000
0#
#565000
b10011 4
b1010 -
b11100 ,
b1010 +
b0 /
01
b11100 (
b1001 *
b1001 $
b1001 '
1#
#570000
0#
#575000
b1010 4
b101100 ,
b1001100 -
b1001100 +
b1 0
b101100 (
1)
b100010 *
b100010 $
b100010 '
1#
#580000
0#
#585000
b1 /
b0 0
11
0)
b1001100 4
b0 ,
b110100 +
b1100100 (
b11000 *
b0 -
b11000 $
b11000 '
1%
1#
#590000
0#
#595000
b0 /
b1 0
01
1)
b0 4
b1000010 -
b1000010 ,
b100010 +
b1000010 (
b1000010 *
b1100 !
b1100 6
b11 "
b11 5
b11 2
b1100 3
b1000010 $
b1000010 '
1#
#600000
0#
#605000
b1 /
b0 0
11
0)
b1000010 4
b0 -
b0 ,
b100000 +
b1100100 (
b100010 *
b100010 $
b100010 '
1#
#610000
0#
#615000
b0 /
b1 0
01
1)
b0 4
b100110 -
b100110 ,
b111110 +
b100110 (
b100110 *
b1101 !
b1101 6
b100 "
b100 5
b100 2
b1101 3
b100110 $
b100110 '
1#
#620000
0#
#625000
b0 0
0)
b100110 4
b1000111 -
b1000111 ,
b101 +
b1000111 (
b100001 *
b100001 $
b100001 '
1#
#630000
0#
#635000
b1000111 4
b101010 ,
b0 +
b1 /
b0 0
11
b10001110 (
0)
b1000111 *
b0 -
b1000111 $
b1000111 '
0%
1#
#640000
0#
#645000
b1 0
1)
b0 4
b1001 ,
b1011011 +
b0 /
01
b1001 (
b1001 *
b1001 -
b1110 !
b1110 6
b101 "
b101 5
b101 2
b1110 3
b1001 $
b1001 '
1%
1#
#650000
0#
#655000
b1 /
11
b1001 4
b0 -
b0 ,
b10010 +
b1100100 (
b1011011 *
b1011011 $
b1011011 '
1#
#660000
0#
#665000
b0 4
b10011 -
b10011 ,
b1010001 +
b0 /
01
b10011 (
b10011 *
b1111 !
b1111 6
b110 "
b110 5
b110 2
b1111 3
b10011 $
b10011 '
1#
#670000
0#
#675000
b1 /
11
b10011 4
b0 -
b0 ,
b100110 +
b1100100 (
b1010001 *
b1010001 $
b1010001 '
1#
#680000
0#
#685000
b0 4
b1000000 -
b1000000 ,
b100100 +
b0 /
01
b1000000 (
b1000000 *
b10000 !
b10000 6
b111 "
b111 5
b111 2
b10000 3
b1000000 $
b1000000 '
1#
#690000
0#
#695000
b1 /
b0 0
11
0)
b1000000 4
b0 -
b0 ,
b11100 +
b1100100 (
b100100 *
b100100 $
b100100 '
1#
#700000
0#
#705000
b1 0
1)
b0 4
b1011 -
b1011 ,
b1011001 +
b0 /
01
b1011 (
b1011 *
b10001 !
b10001 6
b1000 "
b1000 5
b1000 2
b10001 3
b1011 $
b1011 '
1#
#710000
0#
#715000
b0 0
0)
b1011 4
b1101 -
b1101 ,
b1001 +
b1101 (
b10 *
b10 $
b10 '
1#
#720000
0#
#725000
b1101 4
b111010 ,
b1000100 +
b1 0
b111010 (
1)
b101101 *
b1000100 -
b101101 $
b101101 '
0%
1#
#730000
0#
#735000
b1 /
b0 0
11
0)
b1000100 4
b100100 ,
b0 -
b0 +
b10001000 (
b1000100 *
b10010 !
b10010 6
b10010 3
b1000100 $
b1000100 '
1#
#740000
0#
#745000
b1 0
1)
b0 4
b1001001 -
b11011 ,
b1001001 +
b0 /
01
b11011 (
b11011 *
b1001 "
b1001 5
b1001 2
b11011 $
b11011 '
1#
#750000
0#
#755000
b0 0
0)
b1001001 4
b1010100 ,
b111110 -
b111110 +
b1010100 (
b1011 *
b10011 !
b10011 6
b10011 3
b1011 $
b1011 '
1#
#760000
0#
#765000
b111110 4
b100011 -
b1011001 ,
b100011 +
b0 /
01
b1011001 (
b11011 *
b11011 $
b11011 '
1#
#770000
0#
#775000
b100011 4
b1000110 ,
b0 -
b0 +
b1000110 (
b100011 *
b100011 $
b100011 '
1#
#780000
0#
#785000
b0 4
b100 -
b1100000 ,
b100 +
b0 /
b1 0
01
b1100000 (
1)
b1100000 *
b1010 "
b1010 5
b1010 2
b1100000 $
b1100000 '
1#
#790000
0#
#795000
b100 4
b101101 ,
b111111 +
b101101 (
b101001 *
b101101 -
b101001 $
b101001 '
1%
1#
#800000
0#
#805000
b1 /
11
b101101 4
b0 -
b0 ,
b1011010 +
b1100100 (
b110111 *
b110111 $
b110111 '
1#
#810000
0#
#815000
b0 /
01
b0 4
b1011101 -
b1011101 ,
b111 +
b1011101 (
b1011101 *
b10100 !
b10100 6
b1011 "
b1011 5
b1011 2
b10100 3
b1011101 $
b1011101 '
1#
#820000
0#
#825000
b1010110 ,
b0 +
b1 /
b0 0
11
b10111010 (
0)
b1011101 4
b0 -
b10101 !
b10101 6
b10101 3
0%
1#
#830000
0#
#835000
b0 /
b1 0
01
1)
b0 4
b1011100 -
b1000 ,
b1011100 +
b1000 (
b1000 *
b1100 "
b1100 5
b1100 2
b1000 $
b1000 '
1#
#840000
0#
#845000
b1 /
b0 0
11
0)
b1011100 4
b1010100 ,
b0 -
b0 +
b10111000 (
b1011100 *
b10110 !
b10110 6
b10110 3
b1011100 $
b1011100 '
1#
#850000
0#
#855000
b0 /
b1 0
01
1)
b0 4
b1010100 -
b10000 ,
b1010100 +
b10000 (
b10000 *
b1101 "
b1101 5
b1101 2
b10000 $
b10000 '
1#
#860000
0#
#865000
b0 ,
b1000100 +
b1 /
b0 0
11
b1100100 (
0)
b1010100 4
b0 -
1%
1#
#870000
0#
#875000
b0 /
b1 0
01
1)
b0 4
b101010 -
b101010 ,
b111010 +
b101010 (
b101010 *
b10111 !
b10111 6
b1110 "
b1110 5
b1110 2
b10111 3
b101010 $
b101010 '
1#
#880000
0#
#885000
b101010 4
b1100000 -
b1100000 ,
b1011000 +
b1100000 (
b110110 *
b110110 $
b110110 '
1#
#890000
0#
#895000
b1 /
11
b1100000 4
b110 ,
b1010110 +
b0 0
b1101010 (
0)
b1010 *
b1010110 -
b11000 !
b11000 6
b11000 3
b1010 $
b1010 '
0%
1#
#900000
0#
#905000
b1010110 4
b0 ,
b1001000 +
b1100100 (
b1110 *
b0 -
b11001 !
b11001 6
b11001 3
b1110 $
b1110 '
1%
1#
#910000
0#
#915000
b0 /
b1 0
01
1)
b0 4
b101001 -
b101001 ,
b111011 +
b101001 (
b101001 *
b11010 !
b11010 6
b1111 "
b1111 5
b1111 2
b11010 3
b101001 $
b101001 '
1#
#920000
0#
#925000
b1 /
11
b101001 4
b0 -
b0 ,
b1010010 +
b1100100 (
b111011 *
b111011 $
b111011 '
1#
#930000
0#
#935000
b0 /
01
b0 4
b111110 -
b111110 ,
b100110 +
b111110 (
b111110 *
b11011 !
b11011 6
b10000 "
b10000 5
b10000 2
b11011 3
b111110 $
b111110 '
1#
#940000
0#
#945000
b1 /
11
b111110 4
b110011 -
b110011 ,
b1001001 +
b10010111 (
b1011001 *
b1011001 $
b1011001 '
1#
#950000
0#
#955000
b110011 4
b11100 -
b11100 ,
b1001010 +
b10000000 (
b1001101 *
b11100 !
b11100 6
b11100 3
b1001101 $
b1001101 '
1#
#960000
0#
#965000
b11100 4
b101001 -
b101001 ,
b1111 +
b0 /
b0 0
01
b101001 (
0)
b1101 *
b11101 !
b11101 6
b11101 3
b1101 $
b1101 '
1#
#970000
0#
#975000
b101001 4
b1100000 ,
b1010110 +
b1 0
b1100000 (
1)
b110111 *
b1010110 -
b110111 $
b110111 '
0%
1#
#980000
0#
#985000
b1010110 4
b1010111 ,
b1010101 -
b1010101 +
b0 0
b1010111 (
0)
b1 *
b11110 !
b11110 6
b11110 3
b1 $
b1 '
1#
#990000
0#
#995000
b1010101 4
b0 ,
b1000110 +
b1 /
11
b1100100 (
b1111 *
b0 -
b1111 $
b1111 '
1%
1#
#1000000
0#
#1005000
b0 /
b1 0
01
1)
b0 4
b111000 -
b111000 ,
b101100 +
b111000 (
b111000 *
b11111 !
b11111 6
b10001 "
b10001 5
b10001 2
b11111 3
b111000 $
b111000 '
1#
#1010000
0#
#1015000
b1100 ,
b0 +
b1 /
b0 0
11
b1110000 (
0)
b111000 4
b0 -
b100000 !
b100000 6
b100000 3
0%
1#
#1020000
0#
#1025000
b1 0
1)
b0 4
b1001000 -
b11100 ,
b1001000 +
b0 /
01
b11100 (
b11100 *
b10010 "
b10010 5
b10010 2
b11100 $
b11100 '
1#
#1030000
0#
#1035000
b1 /
11
b1001000 4
b111000 ,
b1011000 +
b10011100 (
b1010100 *
b111000 -
b1010100 $
b1010100 '
1%
1#
#1040000
0#
#1045000
b0 /
01
b111000 4
b1010100 ,
b11100 +
b0 0
b1010100 (
0)
b11100 *
b11100 -
b100001 !
b100001 6
b100001 3
b11100 $
b11100 '
0%
1#
#1050000
0#
#1055000
b1 0
1)
b11100 4
b1000100 ,
b1011000 -
b1011000 +
b1000100 (
b101000 *
b101000 $
b101000 '
1#
#1060000
0#
#1065000
b1 /
11
b1011000 4
b1111 ,
b111101 +
b0 0
b1110011 (
0)
b11011 *
b1111 -
b100101 !
b100101 6
b100101 3
b100 .
b110101011 $
b110101011 '
1%
1#
#1070000
0#
#1075000
b0 /
b1 0
01
1)
b1111 4
b110111 ,
b1001011 +
b110111 (
b101000 *
b1001011 -
b101000 !
b101000 6
b101000 3
b11 .
b101010100 $
b101010100 '
0%
1#
#1080000
0#
#1085000
b1 /
b0 0
11
0)
b1001011 4
b110010 ,
b0 -
b0 +
b10010110 (
b1001011 *
b101001 !
b101001 6
b101001 3
b0 .
b1001011 $
b1001011 '
1#
#1090000
0#
#1095000
b0 /
01
b0 4
b1010010 ,
b10010 +
b1 0
b1010010 (
1)
b1010010 *
b1010010 -
b101010 !
b101010 6
b10011 "
b10011 5
b10011 2
b101010 3
b1010010 $
b1010010 '
1%
1#
#1100000
0#
#1105000
b0 0
0)
b1010010 4
b1010100 ,
b1010000 +
b1010100 (
b10 *
b1010000 -
b101011 !
b101011 6
b101011 3
b10 $
b10 '
0%
1#
#1110000
0#
#1115000
b1010000 4
b0 -
b111100 ,
b0 +
b1 /
11
b10100000 (
b1010000 *
b1010000 $
b1010000 '
1#
#1120000
0#
#1125000
b0 /
b1 0
01
1)
b0 4
b11010 ,
b1001010 +
b11010 (
b11010 *
b11010 -
b110101 !
b110101 6
b10100 "
b10100 5
b10100 2
b110101 3
b1001 .
b1110011110 $
b1110011110 '
1%
1#
#1130000
0#
#1135000
b1 /
11
b11010 4
b0 -
b0 ,
b110100 +
b1100100 (
b1001010 *
b0 .
b1001010 $
b1001010 '
1#
#1140000
0#
#1145000
b0 4
b101110 ,
b110110 +
b0 /
01
b101110 (
b101110 *
b110110 -
b111110 !
b111110 6
b10101 "
b10101 5
b10101 2
b111110 3
b1000 .
b1101001110 $
b1101001110 '
0%
1#
#1150000
0#
#1155000
b0 0
0)
b110110 4
b1010011 ,
b11001 +
b1010011 (
b11101 *
b1010011 -
b0 .
b11101 $
b11101 '
1%
1#
#1160000
0#
#1165000
b1010011 4
b1100000 ,
b1000110 +
b1100000 (
b1101 *
b1000110 -
b1101 $
b1101 '
0%
1#
#1170000
0#
#1175000
b1000110 4
b101011 -
b1100001 ,
b101011 +
b0 /
01
b1100001 (
b11011 *
b11011 $
b11011 '
1#
#1180000
0#
#1185000
b101011 4
b111010 ,
b11100 -
b11100 +
b111010 (
b1111 *
b1111 $
b1111 '
1#
#1190000
0#
#1195000
b11100 4
b111000 ,
b0 -
b0 +
b111000 (
b11100 *
b1000110 !
b1000110 6
b1000110 3
b1000 .
b1100111100 $
b1100111100 '
1#
#1200000
0#
#1205000
b0 4
b1001011 ,
b11001 +
b0 /
b1 0
01
b1001011 (
1)
b1001011 *
b1001011 -
b10110 "
b10110 5
b10110 2
b0 .
b1001011 $
b1001011 '
1%
1#
#1210000
0#
#1215000
b0 0
0)
b1001011 4
b1010001 -
b1010001 ,
b1000101 +
b1010001 (
b110 *
b110 $
b110 '
1#
#1220000
0#
#1225000
b1010001 4
b1000101 ,
b1011101 +
b1 /
b1 0
11
b10101001 (
1)
b1011000 *
b1011101 -
b1001110 !
b1001110 6
b1001110 3
b1000 .
b1101111000 $
b1101111000 '
0%
1#
#1230000
0#
#1235000
b1011101 4
b10010 ,
b1000100 +
b0 0
b1110110 (
0)
b11001 *
b10010 -
b1001111 !
b1001111 6
b1001111 3
b0 .
b11001 $
b11001 '
1%
1#
#1240000
0#
#1245000
b0 /
b1 0
01
1)
b10010 4
b110010 ,
b1010110 +
b110010 (
b100000 *
b1010110 -
b1010101 !
b1010101 6
b1010101 3
b110 .
b1001111000 $
b1001111000 '
0%
1#
#1250000
0#
#1255000
b0 0
0)
b1010110 4
b0 -
b1001000 ,
b0 +
b1 /
11
b10101100 (
b1010110 *
b1010110 !
b1010110 6
b1010110 3
b0 .
b1010110 $
b1010110 '
1#
#1260000
0#
#1265000
b0 /
01
b0 4
b111 -
b1011101 ,
b111 +
b1 0
b1011101 (
1)
b1011101 *
b10111 "
b10111 5
b10111 2
b1011101 $
b1011101 '
1#
#1270000
0#
#1275000
b111 4
b111010 ,
b111000 +
b111010 (
b110011 *
b111010 -
b110011 $
b110011 '
1%
1#
#1280000
0#
#1285000
b0 0
0)
b111010 4
b1000010 ,
b110010 +
b1000010 (
b1000 *
b110010 -
b1011110 !
b1011110 6
b1011110 3
b111 .
b1011000100 $
b1011000100 '
0%
1#
#1290000
0#
#1295000
b110010 4
b111011 ,
b101001 +
b111011 (
b1001 *
b111011 -
b1100010 !
b1100010 6
b1100010 3
b100 .
b110011001 $
b110011001 '
1%
1#
#1300000
0#
#1305000
b1 /
11
b111011 4
b0 -
b0 ,
b10010 +
b1100100 (
b101001 *
b0 .
b101001 $
b101001 '
1#
#1310000
0#
#1315000
b0 /
b1 0
01
1)
b0 4
b110111 ,
b101101 +
b110111 (
b110111 *
b101101 -
b11000 "
b11000 5
b11000 2
b110111 $
b110111 '
0%
1#
#1320000
0#
#1325000
b0 0
0)
b101101 4
b110010 ,
b101000 -
b101000 +
b110010 (
b101 *
b1100011 !
b1100011 6
b1100011 3
b101 $
b101 '
1#
#1330000
0#
#1335000
b101000 4
b0 ,
b1010000 +
b1 /
b1 0
11
b1100100 (
1)
b111100 *
b0 -
b1100111 !
b1100111 6
b1100111 3
b100 .
b111001100 $
b111001100 '
1%
1#
#1340000
0#
#1345000
b0 4
b1100 -
b1100 ,
b1011000 +
b0 /
b1 0
01
b1100 (
1)
b1100 *
b1101000 !
b1101000 6
b11001 "
b11001 5
b11001 2
b1101000 3
b0 .
b1100 $
b1100 '
1#
#1350000
0#
#1355000
b1100 4
b1001000 ,
b110100 +
b1001000 (
b111100 *
b110100 -
b1101001 !
b1101001 6
b1101001 3
b111100 $
b111100 '
0%
1#
#1360000
0#
#1365000
b110100 4
b110001 ,
b110111 +
b1 /
11
b10010101 (
b1100001 *
b110001 -
b1100001 $
b1100001 '
1%
1#
#1370000
0#
#1375000
b110001 4
b101001 ,
b111001 +
b10001101 (
b1011100 *
b111001 -
b1101010 !
b1101010 6
b1101010 3
b1011100 $
b1011100 '
0%
1#
#1380000
0#
#1385000
b111001 4
b101101 -
b1000101 ,
b101101 +
b0 /
b0 0
01
b1000101 (
0)
b1100 *
b1101011 !
b1101011 6
b1101011 3
b1100 $
b1100 '
1#
#1390000
0#
#1395000
b101101 4
b1001011 ,
b1111 -
b1111 +
b1001011 (
b11110 *
b1101101 !
b1101101 6
b1101101 3
b10 .
b11100110 $
b11100110 '
1#
#1400000
0#
#1405000
b1111 4
b0 ,
b11110 +
b1 /
b1 0
11
b1100100 (
1)
b1010101 *
b0 -
b0 .
b1010101 $
b1010101 '
1%
1#
#1410000
0#
