day-1/verilog/src/mod100_pipelined.v
module mod100_pipelined (
    input  wire        clk,
    input  wire        rst,
    input  wire [31:0] in_data,
    output reg  [7:0]  rot_by 
);

    // constant = floor(2^32 / 100) = magic number for fast division
    localparam MAGIC = 32'd42949673;
    
    // Since we're pipelining, we need pipeline register to store data
    reg [31:0] in_s0;

    reg [63:0] mult_s1;
    reg [31:0] in_s1;

    reg [31:0] q_s2;
    reg [31:0] in_s2;

    reg [31:0] r_s3;

    // -Stage 1 - Taking the data in
    always @(posedge clk or posedge rst) begin
        if (rst)
            in_s0 <= 0;
        else
            in_s0 <= in_data;
    end

    // Stage 2 - Multiplying the magic number and storing into S1
    always @(posedge clk or posedge rst) begin
        if (rst) begin
            mult_s1 <= 0;
            in_s1   <= 0;
        end else begin
            mult_s1 <= in_s0 * MAGIC;   // 64-bit product
            in_s1   <= in_s0;
        end
    end

    // Stage 3 - Bit shifting down to get the approximate quotient
    always @(posedge clk or posedge rst) begin
        if (rst) begin
            q_s2 <= 0;
            in_s2 <= 0;
        end else begin
            q_s2 <= mult_s1 >> 32;      // approximate quotient
            in_s2 <= in_s1;
        end
    end

    // Getting the final output by pushing it into the correct range.
    always @(posedge clk or posedge rst) begin
        if (rst) begin
            r_s3   <= 0;
            rot_by <= 0;
        end else begin
            // compute remainder
            rot_by <= (in_s2 - (q_s2 * 32'd100)) & 32'h000000FF;
        end
    end

endmodule

Advent of FPGA (Verilog or SystemVerilog)/day-1/src/testbenches/mod100_test/mod100_tb.v
`timescale 1ns/1ps

module mod100_tb();
    
    //Inputs to the module
    reg         clk;
    reg         rst;
    reg [31:0]  in_data;
    wire [7:0]  rot_by;


    //Instantiating the Module
    mod100_pipelined uut(
        .clk(clk),
        .rst(rst),
        .in_data(in_data),
        .rot_by(rot_by)
    );

    //Clock generation
    initial begin
        clk = 0;
        rst = 0;
    end
    always #5 clk = ~clk;

    initial begin
        $dumpfile("mod100_tb.vcd");
        $dumpvars(0, mod100_tb);

        //Reset sequence
        @(posedge clk);
        rst = 1;
        in_data = 0;

        @(posedge clk);
        rst = 0;

        //Test Vectors
        @(posedge clk); in_data = 31'd125; 
        @(posedge clk); in_data = 31'd27; 
        @(posedge clk); in_data = 31'd783; 
        @(posedge clk); in_data = 31'd1089; 
        @(posedge clk); in_data = 31'd7779; 

        //Allow pipeline to flush
        repeat (10) @(posedge clk);

        $display("Simulation Done");
        $finish;
    end

endmodule

day-1/verilog/src/testbenches/mod100_test/mod100_tb.vcd
$date
	Tue Dec  9 01:01:39 2025
$end
$version
	Icarus Verilog
$end
$timescale
	1ps
$end
$scope module mod100_tb $end
$var wire 8 ! rot_by [7:0] $end
$var reg 1 " clk $end
$var reg 32 # in_data [31:0] $end
$var reg 1 $ rst $end
$scope module uut $end
$var wire 1 " clk $end
$var wire 32 % in_data [31:0] $end
$var wire 1 $ rst $end
$var parameter 32 & MAGIC $end
$var reg 32 ' in_s0 [31:0] $end
$var reg 32 ( in_s1 [31:0] $end
$var reg 32 ) in_s2 [31:0] $end
$var reg 64 * mult_s1 [63:0] $end
$var reg 32 + q_s2 [31:0] $end
$var reg 32 , r_s3 [31:0] $end
$var reg 8 - rot_by [7:0] $end
$upscope $end
$upscope $end
$enddefinitions $end
$comment Show the parameter values. $end
$dumpall
b10100011110101110000101001 &
$end
#0
$dumpvars
bx -
bx ,
bx +
bx *
bx )
bx (
bx '
bx %
0$
bx #
0"
bx !
$end
#5000
b0 '
b0 (
b0 *
b0 )
b0 +
b0 !
b0 -
b0 ,
b0 #
b0 %
1$
1"
#10000
0"
#15000
0$
1"
#20000
0"
#25000
b1111101 '
b1111101 #
b1111101 %
1"
#30000
0"
#35000
b1111101 (
b101000000000000000000000000000101 *
b11011 '
b11011 #
b11011 %
1"
#40000
0"
#45000
b1100001111 '
b11011 (
b1000101000111101011100001010011 *
b1111101 )
b1 +
b1100001111 #
b1100001111 %
1"
#50000
0"
#55000
b11001 ,
b11011 )
b0 +
b1100001111 (
b11111010100011110101110000101100111 *
b10001000001 '
b10001000001 #
b10001000001 %
1"
#60000
0"
#65000
b1111001100011 '
b10001000001 (
b101011100011110101110000101001101001 *
b1100001111 )
b111 +
b11001 !
b11001 -
b11011 ,
b1111001100011 #
b1111001100011 %
1"
#70000
0"
#75000
b11011 !
b11011 -
b1010011 ,
b10001000001 )
b1010 +
b1111001100011 (
b100110111001010001111010111000111011011 *
1"
#80000
0"
#85000
b1111001100011 )
b1001101 +
b1010011 !
b1010011 -
b1011001 ,
1"
#90000
0"
#95000
b1011001 !
b1011001 -
b1001111 ,
1"
#100000
0"
#105000
b1001111 !
b1001111 -
1"
